Workbook

Sheet Cover
B3: CONFIDENTIAL
B5: Project Chinois
B6: Chinese Wine Bistro — Financial Model
B8: 3-Year Financial Forecast
B9: Draft v1.0 — March 2026
B12: Total Investment | C12: =Investment!C15
B13: Year 1 Revenue (Projected) | C13: ='P&L'!O6
B14: Year 1 EBITDA (Projected) | C14: ='P&L'!O30
B15: Year 1 EBITDA Margin | C15: ='P&L'!O31
B16: Payback Period (months) | C16: =Investment!C28
B19: Prepared for: The Wine Company Limited
B20: All figures in HKD unless otherwise stated

Sheet Assumptions
B1: MASTER ASSUMPTIONS
B2: Blue cells = inputs / Yellow highlight = key assumptions
B4: VENUE & CAPACITY | F4: STAFFING (Monthly Salary HKD)
B5: VIP Room 1 — Seats | C5: 6 | D5: Small private room | F5: Position | G5: Headcount | H5: Monthly Salary
B6: VIP Room 2 — Seats | C6: 12 | D6: Large private room | F6: Restaurant Manager | G6: 1 | H6: 35000
B7: Main / Outdoor Area — Seats | C7: 30 | F7: Sommelier | G7: 1 | H7: 33000
B8: Total Seats | C8: =C5+C6+C7 | F8: Waiter 1 (Senior) | G8: 1 | H8: 24000
B9: Operating Days per Week | C9: 7 | F9: Waiter 2 | G9: 1 | H9: 20000
B10: Lunch Service | C10: Yes | D10: 1 turn lunch | F10: Waiter 3 | G10: 1 | H10: 20000
F11: Waiter 4 | G11: 1 | H11: 20000
F12: Waiter 5 | G12: 1 | H12: 20000
B13: Dinner Service | C13: Yes | D13: 1 turn dinner | F13: Part-time FOH (est.) | G13: 1 | H13: 14000
B14: Lunch + Dinner (see Revenue tab) | C14: 2 | D14: Lunch + Dinner | F14: Head Chef | G14: 1 | H14: 38000
F15: Sous Chef | G15: 1 | H15: 28000
B16: PER HEAD SPENDING (HKD) | F16: Kitchen Staff 1 | G16: 1 | H16: 20000
B17: DINNER | F17: Kitchen Staff 2 | G17: 1 | H17: 18000
B18: VIP Room — Dinner Per Head (incl. wine) | C18: 1600 | D18: Same as v1 | F18: Kitchen Staff 3 | G18: 1 | H18: 18000
B19: Main Area — Dinner Per Head (incl. wine) | C19: 1000 | F19: Dishwashing Staff | G19: 1 | H19: 16000
B20: Dinner Food % of Spend | C20: 0.65 | D20: Wine = 35% | F20: Total Headcount | G20: =SUM(G6:G19)
F21: Total Monthly Salary | H21: =G6*H6+G7*H7+G8*H8+G9*H9+G10*H10+G11*H11+G12*H12+G13*H13+G14*H14+G15*H15+G16*H16+G17*H17+G18*H18+G19*H19
B22: LUNCH | F22: MPF Employer Contribution % | H22: 0.05
B23: VIP Room — Lunch Per Head (incl. wine) | C23: 500 | F23: Total Monthly Staff Cost (incl. MPF) | G23: 1 | H23: =H21*(1+H22)
B24: Main Area — Lunch Per Head (incl. wine) | C24: 200 | F24: Kitchen Staff 3 | G24: 1 | H24: 18000
B25: Lunch Food % of Spend | C25: 0.9 | D25: Wine = 10% | F25: Dishwashing Staff | G25: 1 | H25: 16000
B26: Service Charge Rate | C26: 0.1 | F26: Total Headcount | G26: =SUM(G6:G19)
F27: Total Monthly Salary | H27: =G6*H6+G7*H7+G8*H8+G9*H9+G10*H10+G11*H11+G12*H12+G13*H13+G14*H14+G15*H15+G16*H16+G17*H17+G18*H18+G19*H19
B28: OCCUPANCY RAMP-UP (% of capacity) | F28: MPF Employer Contribution % | H28: 0.05 | I28: Capped at $1,500/employee
B29: Months 1-3 (Soft Opening) | C29: 0.35 | D29: Ramp-up period | F29: Total Monthly Staff Cost (incl. MPF) | H29: =H21*(1+H22)
B30: Months 4-6 | C30: 0.5
B31: Months 7-9 | C31: 0.6 | F31: RENT & FIXED COSTS (Monthly HKD)
B32: Months 10-12 | C32: 0.7 | F32: Base Rent (Fixed) | H32: 140000 | I32: Monthly
B33: Year 2 Average | C33: 0.75 | D33: Mature operations | F33: Variable Rent (% of Revenue) | H33: 0 | I33: Turnover rent above base
B34: Year 3 Average | C34: 0.8 | F34: Building Management Fee | H34: 22000
B35: VIP Room Occupancy Discount | C35: 0.7 | D35: VIP rooms fill at 70% of main area rate | F35: Electricity / Water / Gas | H35: 18000
F36: Insurance | H36: 3000
B37: DISCOUNT & PRICING | F37: Rates | H37: 4000
B38: Shareholder Revenue % | C38: 0.1 | D38: % of gross revenue from shareholders | F38: Cleaning | H38: 12000
B39: Shareholder Discount Rate | C39: 0.2 | F39: Credit Card Processing Fee % | H39: 0.02 | I39: % of total revenue
B40: Friends/Special Guest Revenue % | C40: 0.1 | F40: Marketing / PR (Monthly) | H40: 15000
B41: Friends/Special Guest Discount | C41: 0.1 | F41: Consulting & Accounting | H41: 36000
B42: Blended Discount Rate | C42: =C38*C39+C40*C41 | D42: Weighted average discount | F42: Restaurant Supplies | H42: 8000
F43: Subscriptions & Telecom | H43: 3000
B44: COST OF GOODS SOLD | F44: Other / Miscellaneous | H44: 5000
B45: Food Cost % | C45: 0.3 | D45: % of net food revenue | F45: Garbage / Disposal | H45: 3000
B46: Wine / Beverage Cost % | C46: 0.5 | D46: % of net wine revenue | F46: Repairs & Maintenance | H46: 5000
F47: Staff Welfare & Benefits | H47: 8000
F49: GROWTH & INFLATION
F50: Annual Menu Price Increase | H50: 0.03 | I50: Applied from Year 2
F51: Annual Salary Increase | H51: 0.03
F52: Annual OpEx Inflation | H52: 0.025
F53: Management Incentive Fee % | H53: 0.12 | I53: % of EBITDA, same as Aroma

Sheet Revenue
B1: REVENUE BUILD
C3: M1 | D3: M2 | E3: M3 | F3: M4 | G3: M5 | H3: M6 | I3: M7 | J3: M8 | K3: M9 | L3: M10 | M3: M11 | N3: M12 | O3: Year 1 | P3: M13 | Q3: M14 | R3: M15 | S3: M16 | T3: M17 | U3: M18 | V3: M19 | W3: M20 | X3: M21 | Y3: M22 | Z3: M23 | AA3: M24 | AB3: Year 2 | AC3: M25 | AD3: M26 | AE3: M27 | AF3: M28 | AG3: M29 | AH3: M30 | AI3: M31 | AJ3: M32 | AK3: M33 | AL3: M34 | AM3: M35 | AN3: M36 | AO3: Year 3
B4: Operating Days | C4: 30 | D4: 30 | E4: 30 | F4: 30 | G4: 30 | H4: 30 | I4: 30 | J4: 30 | K4: 30 | L4: 30 | M4: 30 | N4: 30 | O4: =SUM(C4:N4) | P4: 30 | Q4: 30 | R4: 30 | S4: 30 | T4: 30 | U4: 30 | V4: 30 | W4: 30 | X4: 30 | Y4: 30 | Z4: 30 | AA4: 30 | AB4: =SUM(P4:AA4) | AC4: 30 | AD4: 30 | AE4: 30 | AF4: 30 | AG4: 30 | AH4: 30 | AI4: 30 | AJ4: 30 | AK4: 30 | AL4: 30 | AM4: 30 | AN4: 30 | AO4: =SUM(AC4:AN4)
B5: Main Area Occupancy Rate | C5: =Assumptions!C29 | D5: =Assumptions!C29 | E5: =Assumptions!C29 | F5: =Assumptions!C30 | G5: =Assumptions!C30 | H5: =Assumptions!C30 | I5: =Assumptions!C31 | J5: =Assumptions!C31 | K5: =Assumptions!C31 | L5: =Assumptions!C32 | M5: =Assumptions!C32 | N5: =Assumptions!C32 | O5: =AVERAGE(C5:N5) | P5: =Assumptions!C33 | Q5: =Assumptions!C33 | R5: =Assumptions!C33 | S5: =Assumptions!C33 | T5: =Assumptions!C33 | U5: =Assumptions!C33 | V5: =Assumptions!C33 | W5: =Assumptions!C33 | X5: =Assumptions!C33 | Y5: =Assumptions!C33 | Z5: =Assumptions!C33 | AA5: =Assumptions!C33 | AB5: =AVERAGE(P5:AA5) | AC5: =Assumptions!C34 | AD5: =Assumptions!C34 | AE5: =Assumptions!C34 | AF5: =Assumptions!C34 | AG5: =Assumptions!C34 | AH5: =Assumptions!C34 | AI5: =Assumptions!C34 | AJ5: =Assumptions!C34 | AK5: =Assumptions!C34 | AL5: =Assumptions!C34 | AM5: =Assumptions!C34 | AN5: =Assumptions!C34 | AO5: =AVERAGE(AC5:AN5)
B6: VIP Room Occupancy Rate | C6: =C5*Assumptions!C35 | D6: =D5*Assumptions!C35 | E6: =E5*Assumptions!C35 | F6: =F5*Assumptions!C35 | G6: =G5*Assumptions!C35 | H6: =H5*Assumptions!C35 | I6: =I5*Assumptions!C35 | J6: =J5*Assumptions!C35 | K6: =K5*Assumptions!C35 | L6: =L5*Assumptions!C35 | M6: =M5*Assumptions!C35 | N6: =N5*Assumptions!C35 | O6: =AVERAGE(C6:N6) | P6: =P5*Assumptions!C35 | Q6: =Q5*Assumptions!C35 | R6: =R5*Assumptions!C35 | S6: =S5*Assumptions!C35 | T6: =T5*Assumptions!C35 | U6: =U5*Assumptions!C35 | V6: =V5*Assumptions!C35 | W6: =W5*Assumptions!C35 | X6: =X5*Assumptions!C35 | Y6: =Y5*Assumptions!C35 | Z6: =Z5*Assumptions!C35 | AA6: =AA5*Assumptions!C35 | AB6: =AVERAGE(P6:AA6) | AC6: =AC5*Assumptions!C35 | AD6: =AD5*Assumptions!C35 | AE6: =AE5*Assumptions!C35 | AF6: =AF5*Assumptions!C35 | AG6: =AG5*Assumptions!C35 | AH6: =AH5*Assumptions!C35 | AI6: =AI5*Assumptions!C35 | AJ6: =AJ5*Assumptions!C35 | AK6: =AK5*Assumptions!C35 | AL6: =AL5*Assumptions!C35 | AM6: =AM5*Assumptions!C35 | AN6: =AN5*Assumptions!C35 | AO6: =AVERAGE(AC6:AN6)
B7: Menu Price Multiplier | C7: 1 | D7: 1 | E7: 1 | F7: 1 | G7: 1 | H7: 1 | I7: 1 | J7: 1 | K7: 1 | L7: 1 | M7: 1 | N7: 1 | O7: =AVERAGE(C7:N7) | P7: =1+Assumptions!H50 | Q7: =1+Assumptions!H50 | R7: =1+Assumptions!H50 | S7: =1+Assumptions!H50 | T7: =1+Assumptions!H50 | U7: =1+Assumptions!H50 | V7: =1+Assumptions!H50 | W7: =1+Assumptions!H50 | X7: =1+Assumptions!H50 | Y7: =1+Assumptions!H50 | Z7: =1+Assumptions!H50 | AA7: =1+Assumptions!H50 | AB7: =AVERAGE(P7:AA7) | AC7: =(1+Assumptions!H50)^2 | AD7: =(1+Assumptions!H50)^2 | AE7: =(1+Assumptions!H50)^2 | AF7: =(1+Assumptions!H50)^2 | AG7: =(1+Assumptions!H50)^2 | AH7: =(1+Assumptions!H50)^2 | AI7: =(1+Assumptions!H50)^2 | AJ7: =(1+Assumptions!H50)^2 | AK7: =(1+Assumptions!H50)^2 | AL7: =(1+Assumptions!H50)^2 | AM7: =(1+Assumptions!H50)^2 | AN7: =(1+Assumptions!H50)^2 | AO7: =AVERAGE(AC7:AN7)
B9: DINNER REVENUE
B10: VIP Room 1 (6 pax) — Dinner | C10: =Assumptions!C5*Assumptions!C18*C4*C6*C7 | D10: =Assumptions!C5*Assumptions!C18*D4*D6*D7 | E10: =Assumptions!C5*Assumptions!C18*E4*E6*E7 | F10: =Assumptions!C5*Assumptions!C18*F4*F6*F7 | G10: =Assumptions!C5*Assumptions!C18*G4*G6*G7 | H10: =Assumptions!C5*Assumptions!C18*H4*H6*H7 | I10: =Assumptions!C5*Assumptions!C18*I4*I6*I7 | J10: =Assumptions!C5*Assumptions!C18*J4*J6*J7 | K10: =Assumptions!C5*Assumptions!C18*K4*K6*K7 | L10: =Assumptions!C5*Assumptions!C18*L4*L6*L7 | M10: =Assumptions!C5*Assumptions!C18*M4*M6*M7 | N10: =Assumptions!C5*Assumptions!C18*N4*N6*N7 | O10: =SUM(C10:N10) | P10: =Assumptions!C5*Assumptions!C18*P4*P6*P7 | Q10: =Assumptions!C5*Assumptions!C18*Q4*Q6*Q7 | R10: =Assumptions!C5*Assumptions!C18*R4*R6*R7 | S10: =Assumptions!C5*Assumptions!C18*S4*S6*S7 | T10: =Assumptions!C5*Assumptions!C18*T4*T6*T7 | U10: =Assumptions!C5*Assumptions!C18*U4*U6*U7 | V10: =Assumptions!C5*Assumptions!C18*V4*V6*V7 | W10: =Assumptions!C5*Assumptions!C18*W4*W6*W7 | X10: =Assumptions!C5*Assumptions!C18*X4*X6*X7 | Y10: =Assumptions!C5*Assumptions!C18*Y4*Y6*Y7 | Z10: =Assumptions!C5*Assumptions!C18*Z4*Z6*Z7 | AA10: =Assumptions!C5*Assumptions!C18*AA4*AA6*AA7 | AB10: =SUM(P10:AA10) | AC10: =Assumptions!C5*Assumptions!C18*AC4*AC6*AC7 | AD10: =Assumptions!C5*Assumptions!C18*AD4*AD6*AD7 | AE10: =Assumptions!C5*Assumptions!C18*AE4*AE6*AE7 | AF10: =Assumptions!C5*Assumptions!C18*AF4*AF6*AF7 | AG10: =Assumptions!C5*Assumptions!C18*AG4*AG6*AG7 | AH10: =Assumptions!C5*Assumptions!C18*AH4*AH6*AH7 | AI10: =Assumptions!C5*Assumptions!C18*AI4*AI6*AI7 | AJ10: =Assumptions!C5*Assumptions!C18*AJ4*AJ6*AJ7 | AK10: =Assumptions!C5*Assumptions!C18*AK4*AK6*AK7 | AL10: =Assumptions!C5*Assumptions!C18*AL4*AL6*AL7 | AM10: =Assumptions!C5*Assumptions!C18*AM4*AM6*AM7 | AN10: =Assumptions!C5*Assumptions!C18*AN4*AN6*AN7 | AO10: =SUM(AC10:AN10)
B11: VIP Room 2 (12 pax) — Dinner | C11: =Assumptions!C6*Assumptions!C18*C4*C6*C7 | D11: =Assumptions!C6*Assumptions!C18*D4*D6*D7 | E11: =Assumptions!C6*Assumptions!C18*E4*E6*E7 | F11: =Assumptions!C6*Assumptions!C18*F4*F6*F7 | G11: =Assumptions!C6*Assumptions!C18*G4*G6*G7 | H11: =Assumptions!C6*Assumptions!C18*H4*H6*H7 | I11: =Assumptions!C6*Assumptions!C18*I4*I6*I7 | J11: =Assumptions!C6*Assumptions!C18*J4*J6*J7 | K11: =Assumptions!C6*Assumptions!C18*K4*K6*K7 | L11: =Assumptions!C6*Assumptions!C18*L4*L6*L7 | M11: =Assumptions!C6*Assumptions!C18*M4*M6*M7 | N11: =Assumptions!C6*Assumptions!C18*N4*N6*N7 | O11: =SUM(C11:N11) | P11: =Assumptions!C6*Assumptions!C18*P4*P6*P7 | Q11: =Assumptions!C6*Assumptions!C18*Q4*Q6*Q7 | R11: =Assumptions!C6*Assumptions!C18*R4*R6*R7 | S11: =Assumptions!C6*Assumptions!C18*S4*S6*S7 | T11: =Assumptions!C6*Assumptions!C18*T4*T6*T7 | U11: =Assumptions!C6*Assumptions!C18*U4*U6*U7 | V11: =Assumptions!C6*Assumptions!C18*V4*V6*V7 | W11: =Assumptions!C6*Assumptions!C18*W4*W6*W7 | X11: =Assumptions!C6*Assumptions!C18*X4*X6*X7 | Y11: =Assumptions!C6*Assumptions!C18*Y4*Y6*Y7 | Z11: =Assumptions!C6*Assumptions!C18*Z4*Z6*Z7 | AA11: =Assumptions!C6*Assumptions!C18*AA4*AA6*AA7 | AB11: =SUM(P11:AA11) | AC11: =Assumptions!C6*Assumptions!C18*AC4*AC6*AC7 | AD11: =Assumptions!C6*Assumptions!C18*AD4*AD6*AD7 | AE11: =Assumptions!C6*Assumptions!C18*AE4*AE6*AE7 | AF11: =Assumptions!C6*Assumptions!C18*AF4*AF6*AF7 | AG11: =Assumptions!C6*Assumptions!C18*AG4*AG6*AG7 | AH11: =Assumptions!C6*Assumptions!C18*AH4*AH6*AH7 | AI11: =Assumptions!C6*Assumptions!C18*AI4*AI6*AI7 | AJ11: =Assumptions!C6*Assumptions!C18*AJ4*AJ6*AJ7 | AK11: =Assumptions!C6*Assumptions!C18*AK4*AK6*AK7 | AL11: =Assumptions!C6*Assumptions!C18*AL4*AL6*AL7 | AM11: =Assumptions!C6*Assumptions!C18*AM4*AM6*AM7 | AN11: =Assumptions!C6*Assumptions!C18*AN4*AN6*AN7 | AO11: =SUM(AC11:AN11)
B12: Main / Outdoor (30 pax) — Dinner | C12: =Assumptions!C7*Assumptions!C19*C4*C5*C7 | D12: =Assumptions!C7*Assumptions!C19*D4*D5*D7 | E12: =Assumptions!C7*Assumptions!C19*E4*E5*E7 | F12: =Assumptions!C7*Assumptions!C19*F4*F5*F7 | G12: =Assumptions!C7*Assumptions!C19*G4*G5*G7 | H12: =Assumptions!C7*Assumptions!C19*H4*H5*H7 | I12: =Assumptions!C7*Assumptions!C19*I4*I5*I7 | J12: =Assumptions!C7*Assumptions!C19*J4*J5*J7 | K12: =Assumptions!C7*Assumptions!C19*K4*K5*K7 | L12: =Assumptions!C7*Assumptions!C19*L4*L5*L7 | M12: =Assumptions!C7*Assumptions!C19*M4*M5*M7 | N12: =Assumptions!C7*Assumptions!C19*N4*N5*N7 | O12: =SUM(C12:N12) | P12: =Assumptions!C7*Assumptions!C19*P4*P5*P7 | Q12: =Assumptions!C7*Assumptions!C19*Q4*Q5*Q7 | R12: =Assumptions!C7*Assumptions!C19*R4*R5*R7 | S12: =Assumptions!C7*Assumptions!C19*S4*S5*S7 | T12: =Assumptions!C7*Assumptions!C19*T4*T5*T7 | U12: =Assumptions!C7*Assumptions!C19*U4*U5*U7 | V12: =Assumptions!C7*Assumptions!C19*V4*V5*V7 | W12: =Assumptions!C7*Assumptions!C19*W4*W5*W7 | X12: =Assumptions!C7*Assumptions!C19*X4*X5*X7 | Y12: =Assumptions!C7*Assumptions!C19*Y4*Y5*Y7 | Z12: =Assumptions!C7*Assumptions!C19*Z4*Z5*Z7 | AA12: =Assumptions!C7*Assumptions!C19*AA4*AA5*AA7 | AB12: =SUM(P12:AA12) | AC12: =Assumptions!C7*Assumptions!C19*AC4*AC5*AC7 | AD12: =Assumptions!C7*Assumptions!C19*AD4*AD5*AD7 | AE12: =Assumptions!C7*Assumptions!C19*AE4*AE5*AE7 | AF12: =Assumptions!C7*Assumptions!C19*AF4*AF5*AF7 | AG12: =Assumptions!C7*Assumptions!C19*AG4*AG5*AG7 | AH12: =Assumptions!C7*Assumptions!C19*AH4*AH5*AH7 | AI12: =Assumptions!C7*Assumptions!C19*AI4*AI5*AI7 | AJ12: =Assumptions!C7*Assumptions!C19*AJ4*AJ5*AJ7 | AK12: =Assumptions!C7*Assumptions!C19*AK4*AK5*AK7 | AL12: =Assumptions!C7*Assumptions!C19*AL4*AL5*AL7 | AM12: =Assumptions!C7*Assumptions!C19*AM4*AM5*AM7 | AN12: =Assumptions!C7*Assumptions!C19*AN4*AN5*AN7 | AO12: =SUM(AC12:AN12)
B13: Total Dinner Revenue | C13: =C10+C11+C12 | D13: =D10+D11+D12 | E13: =E10+E11+E12 | F13: =F10+F11+F12 | G13: =G10+G11+G12 | H13: =H10+H11+H12 | I13: =I10+I11+I12 | J13: =J10+J11+J12 | ... N13: =N10+N11+N12 | O13: =SUM(C13:N13) | P13: =P10+P11+P12 | Q13: =Q10+Q11+Q12 | R13: =R10+R11+R12 | S13: =S10+S11+S12 | T13: =T10+T11+T12 | U13: =U10+U11+U12 | V13: =V10+V11+V12 | W13: =W10+W11+W12 | ... AA13: =AA10+AA11+AA12 | AB13: =SUM(P13:AA13) | AC13: =AC10+AC11+AC12 | AD13: =AD10+AD11+AD12 | AE13: =AE10+AE11+AE12 | AF13: =AF10+AF11+AF12 | AG13: =AG10+AG11+AG12 | AH13: =AH10+AH11+AH12 | AI13: =AI10+AI11+AI12 | AJ13: =AJ10+AJ11+AJ12 | ... AN13: =AN10+AN11+AN12 | AO13: =SUM(AC13:AN13)
B15: LUNCH REVENUE
B16: VIP Room 1 (6 pax) — Lunch | C16: =Assumptions!C5*Assumptions!C23*C4*C6*C7 | D16: =Assumptions!C5*Assumptions!C23*D4*D6*D7 | E16: =Assumptions!C5*Assumptions!C23*E4*E6*E7 | F16: =Assumptions!C5*Assumptions!C23*F4*F6*F7 | G16: =Assumptions!C5*Assumptions!C23*G4*G6*G7 | H16: =Assumptions!C5*Assumptions!C23*H4*H6*H7 | I16: =Assumptions!C5*Assumptions!C23*I4*I6*I7 | J16: =Assumptions!C5*Assumptions!C23*J4*J6*J7 | K16: =Assumptions!C5*Assumptions!C23*K4*K6*K7 | L16: =Assumptions!C5*Assumptions!C23*L4*L6*L7 | M16: =Assumptions!C5*Assumptions!C23*M4*M6*M7 | N16: =Assumptions!C5*Assumptions!C23*N4*N6*N7 | O16: =SUM(C16:N16) | P16: =Assumptions!C5*Assumptions!C23*P4*P6*P7 | Q16: =Assumptions!C5*Assumptions!C23*Q4*Q6*Q7 | R16: =Assumptions!C5*Assumptions!C23*R4*R6*R7 | S16: =Assumptions!C5*Assumptions!C23*S4*S6*S7 | T16: =Assumptions!C5*Assumptions!C23*T4*T6*T7 | U16: =Assumptions!C5*Assumptions!C23*U4*U6*U7 | V16: =Assumptions!C5*Assumptions!C23*V4*V6*V7 | W16: =Assumptions!C5*Assumptions!C23*W4*W6*W7 | X16: =Assumptions!C5*Assumptions!C23*X4*X6*X7 | Y16: =Assumptions!C5*Assumptions!C23*Y4*Y6*Y7 | Z16: =Assumptions!C5*Assumptions!C23*Z4*Z6*Z7 | AA16: =Assumptions!C5*Assumptions!C23*AA4*AA6*AA7 | AB16: =SUM(P16:AA16) | AC16: =Assumptions!C5*Assumptions!C23*AC4*AC6*AC7 | AD16: =Assumptions!C5*Assumptions!C23*AD4*AD6*AD7 | AE16: =Assumptions!C5*Assumptions!C23*AE4*AE6*AE7 | AF16: =Assumptions!C5*Assumptions!C23*AF4*AF6*AF7 | AG16: =Assumptions!C5*Assumptions!C23*AG4*AG6*AG7 | AH16: =Assumptions!C5*Assumptions!C23*AH4*AH6*AH7 | AI16: =Assumptions!C5*Assumptions!C23*AI4*AI6*AI7 | AJ16: =Assumptions!C5*Assumptions!C23*AJ4*AJ6*AJ7 | AK16: =Assumptions!C5*Assumptions!C23*AK4*AK6*AK7 | AL16: =Assumptions!C5*Assumptions!C23*AL4*AL6*AL7 | AM16: =Assumptions!C5*Assumptions!C23*AM4*AM6*AM7 | AN16: =Assumptions!C5*Assumptions!C23*AN4*AN6*AN7 | AO16: =SUM(AC16:AN16)
B17: VIP Room 2 (12 pax) — Lunch | C17: =Assumptions!C6*Assumptions!C23*C4*C6*C7 | D17: =Assumptions!C6*Assumptions!C23*D4*D6*D7 | E17: =Assumptions!C6*Assumptions!C23*E4*E6*E7 | F17: =Assumptions!C6*Assumptions!C23*F4*F6*F7 | G17: =Assumptions!C6*Assumptions!C23*G4*G6*G7 | H17: =Assumptions!C6*Assumptions!C23*H4*H6*H7 | I17: =Assumptions!C6*Assumptions!C23*I4*I6*I7 | J17: =Assumptions!C6*Assumptions!C23*J4*J6*J7 | K17: =Assumptions!C6*Assumptions!C23*K4*K6*K7 | L17: =Assumptions!C6*Assumptions!C23*L4*L6*L7 | M17: =Assumptions!C6*Assumptions!C23*M4*M6*M7 | N17: =Assumptions!C6*Assumptions!C23*N4*N6*N7 | O17: =SUM(C17:N17) | P17: =Assumptions!C6*Assumptions!C23*P4*P6*P7 | Q17: =Assumptions!C6*Assumptions!C23*Q4*Q6*Q7 | R17: =Assumptions!C6*Assumptions!C23*R4*R6*R7 | S17: =Assumptions!C6*Assumptions!C23*S4*S6*S7 | T17: =Assumptions!C6*Assumptions!C23*T4*T6*T7 | U17: =Assumptions!C6*Assumptions!C23*U4*U6*U7 | V17: =Assumptions!C6*Assumptions!C23*V4*V6*V7 | W17: =Assumptions!C6*Assumptions!C23*W4*W6*W7 | X17: =Assumptions!C6*Assumptions!C23*X4*X6*X7 | Y17: =Assumptions!C6*Assumptions!C23*Y4*Y6*Y7 | Z17: =Assumptions!C6*Assumptions!C23*Z4*Z6*Z7 | AA17: =Assumptions!C6*Assumptions!C23*AA4*AA6*AA7 | AB17: =SUM(P17:AA17) | AC17: =Assumptions!C6*Assumptions!C23*AC4*AC6*AC7 | AD17: =Assumptions!C6*Assumptions!C23*AD4*AD6*AD7 | AE17: =Assumptions!C6*Assumptions!C23*AE4*AE6*AE7 | AF17: =Assumptions!C6*Assumptions!C23*AF4*AF6*AF7 | AG17: =Assumptions!C6*Assumptions!C23*AG4*AG6*AG7 | AH17: =Assumptions!C6*Assumptions!C23*AH4*AH6*AH7 | AI17: =Assumptions!C6*Assumptions!C23*AI4*AI6*AI7 | AJ17: =Assumptions!C6*Assumptions!C23*AJ4*AJ6*AJ7 | AK17: =Assumptions!C6*Assumptions!C23*AK4*AK6*AK7 | AL17: =Assumptions!C6*Assumptions!C23*AL4*AL6*AL7 | AM17: =Assumptions!C6*Assumptions!C23*AM4*AM6*AM7 | AN17: =Assumptions!C6*Assumptions!C23*AN4*AN6*AN7 | AO17: =SUM(AC17:AN17)
B18: Main / Outdoor (30 pax) — Lunch | C18: =Assumptions!C7*Assumptions!C24*C4*C5*C7 | D18: =Assumptions!C7*Assumptions!C24*D4*D5*D7 | E18: =Assumptions!C7*Assumptions!C24*E4*E5*E7 | F18: =Assumptions!C7*Assumptions!C24*F4*F5*F7 | G18: =Assumptions!C7*Assumptions!C24*G4*G5*G7 | H18: =Assumptions!C7*Assumptions!C24*H4*H5*H7 | I18: =Assumptions!C7*Assumptions!C24*I4*I5*I7 | J18: =Assumptions!C7*Assumptions!C24*J4*J5*J7 | K18: =Assumptions!C7*Assumptions!C24*K4*K5*K7 | L18: =Assumptions!C7*Assumptions!C24*L4*L5*L7 | M18: =Assumptions!C7*Assumptions!C24*M4*M5*M7 | N18: =Assumptions!C7*Assumptions!C24*N4*N5*N7 | O18: =SUM(C18:N18) | P18: =Assumptions!C7*Assumptions!C24*P4*P5*P7 | Q18: =Assumptions!C7*Assumptions!C24*Q4*Q5*Q7 | R18: =Assumptions!C7*Assumptions!C24*R4*R5*R7 | S18: =Assumptions!C7*Assumptions!C24*S4*S5*S7 | T18: =Assumptions!C7*Assumptions!C24*T4*T5*T7 | U18: =Assumptions!C7*Assumptions!C24*U4*U5*U7 | V18: =Assumptions!C7*Assumptions!C24*V4*V5*V7 | W18: =Assumptions!C7*Assumptions!C24*W4*W5*W7 | X18: =Assumptions!C7*Assumptions!C24*X4*X5*X7 | Y18: =Assumptions!C7*Assumptions!C24*Y4*Y5*Y7 | Z18: =Assumptions!C7*Assumptions!C24*Z4*Z5*Z7 | AA18: =Assumptions!C7*Assumptions!C24*AA4*AA5*AA7 | AB18: =SUM(P18:AA18) | AC18: =Assumptions!C7*Assumptions!C24*AC4*AC5*AC7 | AD18: =Assumptions!C7*Assumptions!C24*AD4*AD5*AD7 | AE18: =Assumptions!C7*Assumptions!C24*AE4*AE5*AE7 | AF18: =Assumptions!C7*Assumptions!C24*AF4*AF5*AF7 | AG18: =Assumptions!C7*Assumptions!C24*AG4*AG5*AG7 | AH18: =Assumptions!C7*Assumptions!C24*AH4*AH5*AH7 | AI18: =Assumptions!C7*Assumptions!C24*AI4*AI5*AI7 | AJ18: =Assumptions!C7*Assumptions!C24*AJ4*AJ5*AJ7 | AK18: =Assumptions!C7*Assumptions!C24*AK4*AK5*AK7 | AL18: =Assumptions!C7*Assumptions!C24*AL4*AL5*AL7 | AM18: =Assumptions!C7*Assumptions!C24*AM4*AM5*AM7 | AN18: =Assumptions!C7*Assumptions!C24*AN4*AN5*AN7 | AO18: =SUM(AC18:AN18)
B19: Total Lunch Revenue | C19: =C16+C17+C18 | D19: =D16+D17+D18 | E19: =E16+E17+E18 | F19: =F16+F17+F18 | G19: =G16+G17+G18 | H19: =H16+H17+H18 | I19: =I16+I17+I18 | J19: =J16+J17+J18 | ... N19: =N16+N17+N18 | O19: =SUM(C19:N19) | P19: =P16+P17+P18 | Q19: =Q16+Q17+Q18 | R19: =R16+R17+R18 | S19: =S16+S17+S18 | T19: =T16+T17+T18 | U19: =U16+U17+U18 | V19: =V16+V17+V18 | W19: =W16+W17+W18 | ... AA19: =AA16+AA17+AA18 | AB19: =SUM(P19:AA19) | AC19: =AC16+AC17+AC18 | AD19: =AD16+AD17+AD18 | AE19: =AE16+AE17+AE18 | AF19: =AF16+AF17+AF18 | AG19: =AG16+AG17+AG18 | AH19: =AH16+AH17+AH18 | AI19: =AI16+AI17+AI18 | AJ19: =AJ16+AJ17+AJ18 | ... AN19: =AN16+AN17+AN18 | AO19: =SUM(AC19:AN19)
B20: Service Charge (10%) | C20: =(C13+C18)*Assumptions!C20 | D20: =(D13+D18)*Assumptions!C20 | E20: =(E13+E18)*Assumptions!C20 | F20: =(F13+F18)*Assumptions!C20 | G20: =(G13+G18)*Assumptions!C20 | H20: =(H13+H18)*Assumptions!C20 | I20: =(I13+I18)*Assumptions!C20 | J20: =(J13+J18)*Assumptions!C20 | K20: =(K13+K18)*Assumptions!C20 | L20: =(L13+L18)*Assumptions!C20 | M20: =(M13+M18)*Assumptions!C20 | N20: =(N13+N18)*Assumptions!C20 | O20: =SUM(C20:N20) | P20: =(P13+P18)*Assumptions!C20 | Q20: =(Q13+Q18)*Assumptions!C20 | R20: =(R13+R18)*Assumptions!C20 | S20: =(S13+S18)*Assumptions!C20 | T20: =(T13+T18)*Assumptions!C20 | U20: =(U13+U18)*Assumptions!C20 | V20: =(V13+V18)*Assumptions!C20 | W20: =(W13+W18)*Assumptions!C20 | X20: =(X13+X18)*Assumptions!C20 | Y20: =(Y13+Y18)*Assumptions!C20 | Z20: =(Z13+Z18)*Assumptions!C20 | AA20: =(AA13+AA18)*Assumptions!C20 | AB20: =SUM(P20:AA20) | AC20: =(AC13+AC18)*Assumptions!C20 | AD20: =(AD13+AD18)*Assumptions!C20 | AE20: =(AE13+AE18)*Assumptions!C20 | AF20: =(AF13+AF18)*Assumptions!C20 | AG20: =(AG13+AG18)*Assumptions!C20 | AH20: =(AH13+AH18)*Assumptions!C20 | AI20: =(AI13+AI18)*Assumptions!C20 | AJ20: =(AJ13+AJ18)*Assumptions!C20 | AK20: =(AK13+AK18)*Assumptions!C20 | AL20: =(AL13+AL18)*Assumptions!C20 | AM20: =(AM13+AM18)*Assumptions!C20 | AN20: =(AN13+AN18)*Assumptions!C20 | AO20: =SUM(AC20:AN20)
B21: TOTAL GROSS REVENUE | C21: =C13+C19 | D21: =D13+D19 | E21: =E13+E19 | F21: =F13+F19 | G21: =G13+G19 | H21: =H13+H19 | I21: =I13+I19 | J21: =J13+J19 | ... N21: =N13+N19 | O21: =SUM(C21:N21) | P21: =P13+P19 | Q21: =Q13+Q19 | R21: =R13+R19 | S21: =S13+S19 | T21: =T13+T19 | U21: =U13+U19 | V21: =V13+V19 | W21: =W13+W19 | ... AA21: =AA13+AA19 | AB21: =SUM(P21:AA21) | AC21: =AC13+AC19 | AD21: =AD13+AD19 | AE21: =AE13+AE19 | AF21: =AF13+AF19 | AG21: =AG13+AG19 | AH21: =AH13+AH19 | AI21: =AI13+AI19 | AJ21: =AJ13+AJ19 | ... AN21: =AN13+AN19 | AO21: =SUM(AC21:AN21)
B22: NET REVENUE | C22: =C13+C18+C20 | D22: =D13+D18+D20 | E22: =E13+E18+E20 | F22: =F13+F18+F20 | G22: =G13+G18+G20 | H22: =H13+H18+H20 | I22: =I13+I18+I20 | J22: =J13+J18+J20 | ... N22: =N13+N18+N20 | O22: =SUM(C22:N22) | P22: =P13+P18+P20 | Q22: =Q13+Q18+Q20 | R22: =R13+R18+R20 | S22: =S13+S18+S20 | T22: =T13+T18+T20 | U22: =U13+U18+U20 | V22: =V13+V18+V20 | W22: =W13+W18+W20 | ... AA22: =AA13+AA18+AA20 | AB22: =SUM(P22:AA22) | AC22: =AC13+AC18+AC20 | AD22: =AD13+AD18+AD20 | AE22: =AE13+AE18+AE20 | AF22: =AF13+AF18+AF20 | AG22: =AG13+AG18+AG20 | AH22: =AH13+AH18+AH20 | AI22: =AI13+AI18+AI20 | AJ22: =AJ13+AJ18+AJ20 | ... AN22: =AN13+AN18+AN20 | AO22: =SUM(AC22:AN22)
B23: DISCOUNTS
B24: Shareholder Discount (20% on 10%) | C24: =-C21*Assumptions!C38*Assumptions!C39 | D24: =-D21*Assumptions!C38*Assumptions!C39 | E24: =-E21*Assumptions!C38*Assumptions!C39 | F24: =-F21*Assumptions!C38*Assumptions!C39 | G24: =-G21*Assumptions!C38*Assumptions!C39 | H24: =-H21*Assumptions!C38*Assumptions!C39 | I24: =-I21*Assumptions!C38*Assumptions!C39 | J24: =-J21*Assumptions!C38*Assumptions!C39 | K24: =-K21*Assumptions!C38*Assumptions!C39 | L24: =-L21*Assumptions!C38*Assumptions!C39 | M24: =-M21*Assumptions!C38*Assumptions!C39 | N24: =-N21*Assumptions!C38*Assumptions!C39 | O24: =SUM(C24:N24) | P24: =-P21*Assumptions!C38*Assumptions!C39 | Q24: =-Q21*Assumptions!C38*Assumptions!C39 | R24: =-R21*Assumptions!C38*Assumptions!C39 | S24: =-S21*Assumptions!C38*Assumptions!C39 | T24: =-T21*Assumptions!C38*Assumptions!C39 | U24: =-U21*Assumptions!C38*Assumptions!C39 | V24: =-V21*Assumptions!C38*Assumptions!C39 | W24: =-W21*Assumptions!C38*Assumptions!C39 | X24: =-X21*Assumptions!C38*Assumptions!C39 | Y24: =-Y21*Assumptions!C38*Assumptions!C39 | Z24: =-Z21*Assumptions!C38*Assumptions!C39 | AA24: =-AA21*Assumptions!C38*Assumptions!C39 | AB24: =SUM(P24:AA24) | AC24: =-AC21*Assumptions!C38*Assumptions!C39 | AD24: =-AD21*Assumptions!C38*Assumptions!C39 | AE24: =-AE21*Assumptions!C38*Assumptions!C39 | AF24: =-AF21*Assumptions!C38*Assumptions!C39 | AG24: =-AG21*Assumptions!C38*Assumptions!C39 | AH24: =-AH21*Assumptions!C38*Assumptions!C39 | AI24: =-AI21*Assumptions!C38*Assumptions!C39 | AJ24: =-AJ21*Assumptions!C38*Assumptions!C39 | AK24: =-AK21*Assumptions!C38*Assumptions!C39 | AL24: =-AL21*Assumptions!C38*Assumptions!C39 | AM24: =-AM21*Assumptions!C38*Assumptions!C39 | AN24: =-AN21*Assumptions!C38*Assumptions!C39 | AO24: =SUM(AC24:AN24)
B25: Friends / Special Guest Discount (10% on 10%) | C25: =-C21*Assumptions!C40*Assumptions!C41 | D25: =-D21*Assumptions!C40*Assumptions!C41 | E25: =-E21*Assumptions!C40*Assumptions!C41 | F25: =-F21*Assumptions!C40*Assumptions!C41 | G25: =-G21*Assumptions!C40*Assumptions!C41 | H25: =-H21*Assumptions!C40*Assumptions!C41 | I25: =-I21*Assumptions!C40*Assumptions!C41 | J25: =-J21*Assumptions!C40*Assumptions!C41 | K25: =-K21*Assumptions!C40*Assumptions!C41 | L25: =-L21*Assumptions!C40*Assumptions!C41 | M25: =-M21*Assumptions!C40*Assumptions!C41 | N25: =-N21*Assumptions!C40*Assumptions!C41 | O25: =SUM(C25:N25) | P25: =-P21*Assumptions!C40*Assumptions!C41 | Q25: =-Q21*Assumptions!C40*Assumptions!C41 | R25: =-R21*Assumptions!C40*Assumptions!C41 | S25: =-S21*Assumptions!C40*Assumptions!C41 | T25: =-T21*Assumptions!C40*Assumptions!C41 | U25: =-U21*Assumptions!C40*Assumptions!C41 | V25: =-V21*Assumptions!C40*Assumptions!C41 | W25: =-W21*Assumptions!C40*Assumptions!C41 | X25: =-X21*Assumptions!C40*Assumptions!C41 | Y25: =-Y21*Assumptions!C40*Assumptions!C41 | Z25: =-Z21*Assumptions!C40*Assumptions!C41 | AA25: =-AA21*Assumptions!C40*Assumptions!C41 | AB25: =SUM(P25:AA25) | AC25: =-AC21*Assumptions!C40*Assumptions!C41 | AD25: =-AD21*Assumptions!C40*Assumptions!C41 | AE25: =-AE21*Assumptions!C40*Assumptions!C41 | AF25: =-AF21*Assumptions!C40*Assumptions!C41 | AG25: =-AG21*Assumptions!C40*Assumptions!C41 | AH25: =-AH21*Assumptions!C40*Assumptions!C41 | AI25: =-AI21*Assumptions!C40*Assumptions!C41 | AJ25: =-AJ21*Assumptions!C40*Assumptions!C41 | AK25: =-AK21*Assumptions!C40*Assumptions!C41 | AL25: =-AL21*Assumptions!C40*Assumptions!C41 | AM25: =-AM21*Assumptions!C40*Assumptions!C41 | AN25: =-AN21*Assumptions!C40*Assumptions!C41 | AO25: =SUM(AC25:AN25)
B26: Total Discounts | C26: =C24+C25 | D26: =D24+D25 | E26: =E24+E25 | F26: =F24+F25 | G26: =G24+G25 | H26: =H24+H25 | I26: =I24+I25 | J26: =J24+J25 | ... N26: =N24+N25 | O26: =SUM(C26:N26) | P26: =P24+P25 | Q26: =Q24+Q25 | R26: =R24+R25 | S26: =S24+S25 | T26: =T24+T25 | U26: =U24+U25 | V26: =V24+V25 | W26: =W24+W25 | ... AA26: =AA24+AA25 | AB26: =SUM(P26:AA26) | AC26: =AC24+AC25 | AD26: =AD24+AD25 | AE26: =AE24+AE25 | AF26: =AF24+AF25 | AG26: =AG24+AG25 | AH26: =AH24+AH25 | AI26: =AI24+AI25 | AJ26: =AJ24+AJ25 | ... AN26: =AN24+AN25 | AO26: =SUM(AC26:AN26)
B28: Service Charge (10%) | C28: =(C21+C26)*Assumptions!C26 | D28: =(D21+D26)*Assumptions!C26 | E28: =(E21+E26)*Assumptions!C26 | F28: =(F21+F26)*Assumptions!C26 | G28: =(G21+G26)*Assumptions!C26 | H28: =(H21+H26)*Assumptions!C26 | I28: =(I21+I26)*Assumptions!C26 | J28: =(J21+J26)*Assumptions!C26 | K28: =(K21+K26)*Assumptions!C26 | L28: =(L21+L26)*Assumptions!C26 | M28: =(M21+M26)*Assumptions!C26 | N28: =(N21+N26)*Assumptions!C26 | O28: =SUM(C28:N28) | P28: =(P21+P26)*Assumptions!C26 | Q28: =(Q21+Q26)*Assumptions!C26 | R28: =(R21+R26)*Assumptions!C26 | S28: =(S21+S26)*Assumptions!C26 | T28: =(T21+T26)*Assumptions!C26 | U28: =(U21+U26)*Assumptions!C26 | V28: =(V21+V26)*Assumptions!C26 | W28: =(W21+W26)*Assumptions!C26 | X28: =(X21+X26)*Assumptions!C26 | Y28: =(Y21+Y26)*Assumptions!C26 | Z28: =(Z21+Z26)*Assumptions!C26 | AA28: =(AA21+AA26)*Assumptions!C26 | AB28: =SUM(P28:AA28) | AC28: =(AC21+AC26)*Assumptions!C26 | AD28: =(AD21+AD26)*Assumptions!C26 | AE28: =(AE21+AE26)*Assumptions!C26 | AF28: =(AF21+AF26)*Assumptions!C26 | AG28: =(AG21+AG26)*Assumptions!C26 | AH28: =(AH21+AH26)*Assumptions!C26 | AI28: =(AI21+AI26)*Assumptions!C26 | AJ28: =(AJ21+AJ26)*Assumptions!C26 | AK28: =(AK21+AK26)*Assumptions!C26 | AL28: =(AL21+AL26)*Assumptions!C26 | AM28: =(AM21+AM26)*Assumptions!C26 | AN28: =(AN21+AN26)*Assumptions!C26 | AO28: =SUM(AC28:AN28)
B30: NET REVENUE | C30: =C21+C26+C28 | D30: =D21+D26+D28 | E30: =E21+E26+E28 | F30: =F21+F26+F28 | G30: =G21+G26+G28 | H30: =H21+H26+H28 | I30: =I21+I26+I28 | J30: =J21+J26+J28 | ... N30: =N21+N26+N28 | O30: =SUM(C30:N30) | P30: =P21+P26+P28 | Q30: =Q21+Q26+Q28 | R30: =R21+R26+R28 | S30: =S21+S26+S28 | T30: =T21+T26+T28 | U30: =U21+U26+U28 | V30: =V21+V26+V28 | W30: =W21+W26+W28 | ... AA30: =AA21+AA26+AA28 | AB30: =SUM(P30:AA30) | AC30: =AC21+AC26+AC28 | AD30: =AD21+AD26+AD28 | AE30: =AE21+AE26+AE28 | AF30: =AF21+AF26+AF28 | AG30: =AG21+AG26+AG28 | AH30: =AH21+AH26+AH28 | AI30: =AI21+AI26+AI28 | AJ30: =AJ21+AJ26+AJ28 | ... AN30: =AN21+AN26+AN28 | AO30: =SUM(AC30:AN30)
B32: REVENUE SPLIT (for COGS)
B33: Food Revenue (Dinner) | C33: =IF(C21=0,0,(C13/C21)*(C21+C26)*Assumptions!C20) | D33: =IF(D21=0,0,(D13/D21)*(D21+D26)*Assumptions!C20) | E33: =IF(E21=0,0,(E13/E21)*(E21+E26)*Assumptions!C20) | F33: =IF(F21=0,0,(F13/F21)*(F21+F26)*Assumptions!C20) | G33: =IF(G21=0,0,(G13/G21)*(G21+G26)*Assumptions!C20) | H33: =IF(H21=0,0,(H13/H21)*(H21+H26)*Assumptions!C20) | I33: =IF(I21=0,0,(I13/I21)*(I21+I26)*Assumptions!C20) | J33: =IF(J21=0,0,(J13/J21)*(J21+J26)*Assumptions!C20) | K33: =IF(K21=0,0,(K13/K21)*(K21+K26)*Assumptions!C20) | L33: =IF(L21=0,0,(L13/L21)*(L21+L26)*Assumptions!C20) | M33: =IF(M21=0,0,(M13/M21)*(M21+M26)*Assumptions!C20) | N33: =IF(N21=0,0,(N13/N21)*(N21+N26)*Assumptions!C20) | O33: =SUM(C33:N33) | P33: =IF(P21=0,0,(P13/P21)*(P21+P26)*Assumptions!C20) | Q33: =IF(Q21=0,0,(Q13/Q21)*(Q21+Q26)*Assumptions!C20) | R33: =IF(R21=0,0,(R13/R21)*(R21+R26)*Assumptions!C20) | S33: =IF(S21=0,0,(S13/S21)*(S21+S26)*Assumptions!C20) | T33: =IF(T21=0,0,(T13/T21)*(T21+T26)*Assumptions!C20) | U33: =IF(U21=0,0,(U13/U21)*(U21+U26)*Assumptions!C20) | V33: =IF(V21=0,0,(V13/V21)*(V21+V26)*Assumptions!C20) | W33: =IF(W21=0,0,(W13/W21)*(W21+W26)*Assumptions!C20) | X33: =IF(X21=0,0,(X13/X21)*(X21+X26)*Assumptions!C20) | Y33: =IF(Y21=0,0,(Y13/Y21)*(Y21+Y26)*Assumptions!C20) | Z33: =IF(Z21=0,0,(Z13/Z21)*(Z21+Z26)*Assumptions!C20) | AA33: =IF(AA21=0,0,(AA13/AA21)*(AA21+AA26)*Assumptions!C20) | AB33: =SUM(P33:AA33) | AC33: =IF(AC21=0,0,(AC13/AC21)*(AC21+AC26)*Assumptions!C20) | AD33: =IF(AD21=0,0,(AD13/AD21)*(AD21+AD26)*Assumptions!C20) | AE33: =IF(AE21=0,0,(AE13/AE21)*(AE21+AE26)*Assumptions!C20) | AF33: =IF(AF21=0,0,(AF13/AF21)*(AF21+AF26)*Assumptions!C20) | AG33: =IF(AG21=0,0,(AG13/AG21)*(AG21+AG26)*Assumptions!C20) | AH33: =IF(AH21=0,0,(AH13/AH21)*(AH21+AH26)*Assumptions!C20) | AI33: =IF(AI21=0,0,(AI13/AI21)*(AI21+AI26)*Assumptions!C20) | AJ33: =IF(AJ21=0,0,(AJ13/AJ21)*(AJ21+AJ26)*Assumptions!C20) | AK33: =IF(AK21=0,0,(AK13/AK21)*(AK21+AK26)*Assumptions!C20) | AL33: =IF(AL21=0,0,(AL13/AL21)*(AL21+AL26)*Assumptions!C20) | AM33: =IF(AM21=0,0,(AM13/AM21)*(AM21+AM26)*Assumptions!C20) | AN33: =IF(AN21=0,0,(AN13/AN21)*(AN21+AN26)*Assumptions!C20) | AO33: =SUM(AC33:AN33)
B34: Food Revenue (Lunch) | C34: =IF(C21=0,0,(C19/C21)*(C21+C26)*Assumptions!C25) | D34: =IF(D21=0,0,(D19/D21)*(D21+D26)*Assumptions!C25) | E34: =IF(E21=0,0,(E19/E21)*(E21+E26)*Assumptions!C25) | F34: =IF(F21=0,0,(F19/F21)*(F21+F26)*Assumptions!C25) | G34: =IF(G21=0,0,(G19/G21)*(G21+G26)*Assumptions!C25) | H34: =IF(H21=0,0,(H19/H21)*(H21+H26)*Assumptions!C25) | I34: =IF(I21=0,0,(I19/I21)*(I21+I26)*Assumptions!C25) | J34: =IF(J21=0,0,(J19/J21)*(J21+J26)*Assumptions!C25) | K34: =IF(K21=0,0,(K19/K21)*(K21+K26)*Assumptions!C25) | L34: =IF(L21=0,0,(L19/L21)*(L21+L26)*Assumptions!C25) | M34: =IF(M21=0,0,(M19/M21)*(M21+M26)*Assumptions!C25) | N34: =IF(N21=0,0,(N19/N21)*(N21+N26)*Assumptions!C25) | O34: =SUM(C34:N34) | P34: =IF(P21=0,0,(P19/P21)*(P21+P26)*Assumptions!C25) | Q34: =IF(Q21=0,0,(Q19/Q21)*(Q21+Q26)*Assumptions!C25) | R34: =IF(R21=0,0,(R19/R21)*(R21+R26)*Assumptions!C25) | S34: =IF(S21=0,0,(S19/S21)*(S21+S26)*Assumptions!C25) | T34: =IF(T21=0,0,(T19/T21)*(T21+T26)*Assumptions!C25) | U34: =IF(U21=0,0,(U19/U21)*(U21+U26)*Assumptions!C25) | V34: =IF(V21=0,0,(V19/V21)*(V21+V26)*Assumptions!C25) | W34: =IF(W21=0,0,(W19/W21)*(W21+W26)*Assumptions!C25) | X34: =IF(X21=0,0,(X19/X21)*(X21+X26)*Assumptions!C25) | Y34: =IF(Y21=0,0,(Y19/Y21)*(Y21+Y26)*Assumptions!C25) | Z34: =IF(Z21=0,0,(Z19/Z21)*(Z21+Z26)*Assumptions!C25) | AA34: =IF(AA21=0,0,(AA19/AA21)*(AA21+AA26)*Assumptions!C25) | AB34: =SUM(P34:AA34) | AC34: =IF(AC21=0,0,(AC19/AC21)*(AC21+AC26)*Assumptions!C25) | AD34: =IF(AD21=0,0,(AD19/AD21)*(AD21+AD26)*Assumptions!C25) | AE34: =IF(AE21=0,0,(AE19/AE21)*(AE21+AE26)*Assumptions!C25) | AF34: =IF(AF21=0,0,(AF19/AF21)*(AF21+AF26)*Assumptions!C25) | AG34: =IF(AG21=0,0,(AG19/AG21)*(AG21+AG26)*Assumptions!C25) | AH34: =IF(AH21=0,0,(AH19/AH21)*(AH21+AH26)*Assumptions!C25) | AI34: =IF(AI21=0,0,(AI19/AI21)*(AI21+AI26)*Assumptions!C25) | AJ34: =IF(AJ21=0,0,(AJ19/AJ21)*(AJ21+AJ26)*Assumptions!C25) | AK34: =IF(AK21=0,0,(AK19/AK21)*(AK21+AK26)*Assumptions!C25) | AL34: =IF(AL21=0,0,(AL19/AL21)*(AL21+AL26)*Assumptions!C25) | AM34: =IF(AM21=0,0,(AM19/AM21)*(AM21+AM26)*Assumptions!C25) | AN34: =IF(AN21=0,0,(AN19/AN21)*(AN21+AN26)*Assumptions!C25) | AO34: =SUM(AC34:AN34)
B35: Total Food Revenue | C35: =C33+C34 | D35: =D33+D34 | E35: =E33+E34 | F35: =F33+F34 | G35: =G33+G34 | H35: =H33+H34 | I35: =I33+I34 | J35: =J33+J34 | ... N35: =N33+N34 | O35: =SUM(C35:N35) | P35: =P33+P34 | Q35: =Q33+Q34 | R35: =R33+R34 | S35: =S33+S34 | T35: =T33+T34 | U35: =U33+U34 | V35: =V33+V34 | W35: =W33+W34 | ... AA35: =AA33+AA34 | AB35: =SUM(P35:AA35) | AC35: =AC33+AC34 | AD35: =AD33+AD34 | AE35: =AE33+AE34 | AF35: =AF33+AF34 | AG35: =AG33+AG34 | AH35: =AH33+AH34 | AI35: =AI33+AI34 | AJ35: =AJ33+AJ34 | ... AN35: =AN33+AN34 | AO35: =SUM(AC35:AN35)
B36: Wine Revenue (Dinner) | C36: =IF(C21=0,0,(C13/C21)*(C21+C26)*(1-Assumptions!C20)) | D36: =IF(D21=0,0,(D13/D21)*(D21+D26)*(1-Assumptions!C20)) | E36: =IF(E21=0,0,(E13/E21)*(E21+E26)*(1-Assumptions!C20)) | F36: =IF(F21=0,0,(F13/F21)*(F21+F26)*(1-Assumptions!C20)) | G36: =IF(G21=0,0,(G13/G21)*(G21+G26)*(1-Assumptions!C20)) | H36: =IF(H21=0,0,(H13/H21)*(H21+H26)*(1-Assumptions!C20)) | I36: =IF(I21=0,0,(I13/I21)*(I21+I26)*(1-Assumptions!C20)) | J36: =IF(J21=0,0,(J13/J21)*(J21+J26)*(1-Assumptions!C20)) | K36: =IF(K21=0,0,(K13/K21)*(K21+K26)*(1-Assumptions!C20)) | L36: =IF(L21=0,0,(L13/L21)*(L21+L26)*(1-Assumptions!C20)) | M36: =IF(M21=0,0,(M13/M21)*(M21+M26)*(1-Assumptions!C20)) | N36: =IF(N21=0,0,(N13/N21)*(N21+N26)*(1-Assumptions!C20)) | O36: =SUM(C36:N36) | P36: =IF(P21=0,0,(P13/P21)*(P21+P26)*(1-Assumptions!C20)) | Q36: =IF(Q21=0,0,(Q13/Q21)*(Q21+Q26)*(1-Assumptions!C20)) | R36: =IF(R21=0,0,(R13/R21)*(R21+R26)*(1-Assumptions!C20)) | S36: =IF(S21=0,0,(S13/S21)*(S21+S26)*(1-Assumptions!C20)) | T36: =IF(T21=0,0,(T13/T21)*(T21+T26)*(1-Assumptions!C20)) | U36: =IF(U21=0,0,(U13/U21)*(U21+U26)*(1-Assumptions!C20)) | V36: =IF(V21=0,0,(V13/V21)*(V21+V26)*(1-Assumptions!C20)) | W36: =IF(W21=0,0,(W13/W21)*(W21+W26)*(1-Assumptions!C20)) | X36: =IF(X21=0,0,(X13/X21)*(X21+X26)*(1-Assumptions!C20)) | Y36: =IF(Y21=0,0,(Y13/Y21)*(Y21+Y26)*(1-Assumptions!C20)) | Z36: =IF(Z21=0,0,(Z13/Z21)*(Z21+Z26)*(1-Assumptions!C20)) | AA36: =IF(AA21=0,0,(AA13/AA21)*(AA21+AA26)*(1-Assumptions!C20)) | AB36: =SUM(P36:AA36) | AC36: =IF(AC21=0,0,(AC13/AC21)*(AC21+AC26)*(1-Assumptions!C20)) | AD36: =IF(AD21=0,0,(AD13/AD21)*(AD21+AD26)*(1-Assumptions!C20)) | AE36: =IF(AE21=0,0,(AE13/AE21)*(AE21+AE26)*(1-Assumptions!C20)) | AF36: =IF(AF21=0,0,(AF13/AF21)*(AF21+AF26)*(1-Assumptions!C20)) | AG36: =IF(AG21=0,0,(AG13/AG21)*(AG21+AG26)*(1-Assumptions!C20)) | AH36: =IF(AH21=0,0,(AH13/AH21)*(AH21+AH26)*(1-Assumptions!C20)) | AI36: =IF(AI21=0,0,(AI13/AI21)*(AI21+AI26)*(1-Assumptions!C20)) | AJ36: =IF(AJ21=0,0,(AJ13/AJ21)*(AJ21+AJ26)*(1-Assumptions!C20)) | AK36: =IF(AK21=0,0,(AK13/AK21)*(AK21+AK26)*(1-Assumptions!C20)) | AL36: =IF(AL21=0,0,(AL13/AL21)*(AL21+AL26)*(1-Assumptions!C20)) | AM36: =IF(AM21=0,0,(AM13/AM21)*(AM21+AM26)*(1-Assumptions!C20)) | AN36: =IF(AN21=0,0,(AN13/AN21)*(AN21+AN26)*(1-Assumptions!C20)) | AO36: =SUM(AC36:AN36)
B37: Wine Revenue (Lunch) | C37: =IF(C21=0,0,(C19/C21)*(C21+C26)*(1-Assumptions!C25)) | D37: =IF(D21=0,0,(D19/D21)*(D21+D26)*(1-Assumptions!C25)) | E37: =IF(E21=0,0,(E19/E21)*(E21+E26)*(1-Assumptions!C25)) | F37: =IF(F21=0,0,(F19/F21)*(F21+F26)*(1-Assumptions!C25)) | G37: =IF(G21=0,0,(G19/G21)*(G21+G26)*(1-Assumptions!C25)) | H37: =IF(H21=0,0,(H19/H21)*(H21+H26)*(1-Assumptions!C25)) | I37: =IF(I21=0,0,(I19/I21)*(I21+I26)*(1-Assumptions!C25)) | J37: =IF(J21=0,0,(J19/J21)*(J21+J26)*(1-Assumptions!C25)) | K37: =IF(K21=0,0,(K19/K21)*(K21+K26)*(1-Assumptions!C25)) | L37: =IF(L21=0,0,(L19/L21)*(L21+L26)*(1-Assumptions!C25)) | M37: =IF(M21=0,0,(M19/M21)*(M21+M26)*(1-Assumptions!C25)) | N37: =IF(N21=0,0,(N19/N21)*(N21+N26)*(1-Assumptions!C25)) | O37: =SUM(C37:N37) | P37: =IF(P21=0,0,(P19/P21)*(P21+P26)*(1-Assumptions!C25)) | Q37: =IF(Q21=0,0,(Q19/Q21)*(Q21+Q26)*(1-Assumptions!C25)) | R37: =IF(R21=0,0,(R19/R21)*(R21+R26)*(1-Assumptions!C25)) | S37: =IF(S21=0,0,(S19/S21)*(S21+S26)*(1-Assumptions!C25)) | T37: =IF(T21=0,0,(T19/T21)*(T21+T26)*(1-Assumptions!C25)) | U37: =IF(U21=0,0,(U19/U21)*(U21+U26)*(1-Assumptions!C25)) | V37: =IF(V21=0,0,(V19/V21)*(V21+V26)*(1-Assumptions!C25)) | W37: =IF(W21=0,0,(W19/W21)*(W21+W26)*(1-Assumptions!C25)) | X37: =IF(X21=0,0,(X19/X21)*(X21+X26)*(1-Assumptions!C25)) | Y37: =IF(Y21=0,0,(Y19/Y21)*(Y21+Y26)*(1-Assumptions!C25)) | Z37: =IF(Z21=0,0,(Z19/Z21)*(Z21+Z26)*(1-Assumptions!C25)) | AA37: =IF(AA21=0,0,(AA19/AA21)*(AA21+AA26)*(1-Assumptions!C25)) | AB37: =SUM(P37:AA37) | AC37: =IF(AC21=0,0,(AC19/AC21)*(AC21+AC26)*(1-Assumptions!C25)) | AD37: =IF(AD21=0,0,(AD19/AD21)*(AD21+AD26)*(1-Assumptions!C25)) | AE37: =IF(AE21=0,0,(AE19/AE21)*(AE21+AE26)*(1-Assumptions!C25)) | AF37: =IF(AF21=0,0,(AF19/AF21)*(AF21+AF26)*(1-Assumptions!C25)) | AG37: =IF(AG21=0,0,(AG19/AG21)*(AG21+AG26)*(1-Assumptions!C25)) | AH37: =IF(AH21=0,0,(AH19/AH21)*(AH21+AH26)*(1-Assumptions!C25)) | AI37: =IF(AI21=0,0,(AI19/AI21)*(AI21+AI26)*(1-Assumptions!C25)) | AJ37: =IF(AJ21=0,0,(AJ19/AJ21)*(AJ21+AJ26)*(1-Assumptions!C25)) | AK37: =IF(AK21=0,0,(AK19/AK21)*(AK21+AK26)*(1-Assumptions!C25)) | AL37: =IF(AL21=0,0,(AL19/AL21)*(AL21+AL26)*(1-Assumptions!C25)) | AM37: =IF(AM21=0,0,(AM19/AM21)*(AM21+AM26)*(1-Assumptions!C25)) | AN37: =IF(AN21=0,0,(AN19/AN21)*(AN21+AN26)*(1-Assumptions!C25)) | AO37: =SUM(AC37:AN37)
B38: Total Wine / Beverage Revenue | C38: =C36+C37 | D38: =D36+D37 | E38: =E36+E37 | F38: =F36+F37 | G38: =G36+G37 | H38: =H36+H37 | I38: =I36+I37 | J38: =J36+J37 | ... N38: =N36+N37 | O38: =SUM(C38:N38) | P38: =P36+P37 | Q38: =Q36+Q37 | R38: =R36+R37 | S38: =S36+S37 | T38: =T36+T37 | U38: =U36+U37 | V38: =V36+V37 | W38: =W36+W37 | ... AA38: =AA36+AA37 | AB38: =SUM(P38:AA38) | AC38: =AC36+AC37 | AD38: =AD36+AD37 | AE38: =AE36+AE37 | AF38: =AF36+AF37 | AG38: =AG36+AG37 | AH38: =AH36+AH37 | AI38: =AI36+AI37 | AJ38: =AJ36+AJ37 | ... AN38: =AN36+AN37 | AO38: =SUM(AC38:AN38)

Sheet COGS
B1: COST OF GOODS SOLD
C3: M1 | D3: M2 | E3: M3 | F3: M4 | G3: M5 | H3: M6 | I3: M7 | J3: M8 | K3: M9 | L3: M10 | M3: M11 | N3: M12 | O3: Year 1 | P3: M13 | Q3: M14 | R3: M15 | S3: M16 | T3: M17 | U3: M18 | V3: M19 | W3: M20 | X3: M21 | Y3: M22 | Z3: M23 | AA3: M24 | AB3: Year 2 | AC3: M25 | AD3: M26 | AE3: M27 | AF3: M28 | AG3: M29 | AH3: M30 | AI3: M31 | AJ3: M32 | AK3: M33 | AL3: M34 | AM3: M35 | AN3: M36 | AO3: Year 3
B5: Food COGS (30%) | C5: =Revenue!C35*Assumptions!C45 | D5: =Revenue!D35*Assumptions!C45 | E5: =Revenue!E35*Assumptions!C45 | F5: =Revenue!F35*Assumptions!C45 | G5: =Revenue!G35*Assumptions!C45 | H5: =Revenue!H35*Assumptions!C45 | I5: =Revenue!I35*Assumptions!C45 | J5: =Revenue!J35*Assumptions!C45 | K5: =Revenue!K35*Assumptions!C45 | L5: =Revenue!L35*Assumptions!C45 | M5: =Revenue!M35*Assumptions!C45 | N5: =Revenue!N35*Assumptions!C45 | O5: =SUM(C5:N5) | P5: =Revenue!P35*Assumptions!C45 | Q5: =Revenue!Q35*Assumptions!C45 | R5: =Revenue!R35*Assumptions!C45 | S5: =Revenue!S35*Assumptions!C45 | T5: =Revenue!T35*Assumptions!C45 | U5: =Revenue!U35*Assumptions!C45 | V5: =Revenue!V35*Assumptions!C45 | W5: =Revenue!W35*Assumptions!C45 | X5: =Revenue!X35*Assumptions!C45 | Y5: =Revenue!Y35*Assumptions!C45 | Z5: =Revenue!Z35*Assumptions!C45 | AA5: =Revenue!AA35*Assumptions!C45 | AB5: =SUM(P5:AA5) | AC5: =Revenue!AC35*Assumptions!C45 | AD5: =Revenue!AD35*Assumptions!C45 | AE5: =Revenue!AE35*Assumptions!C45 | AF5: =Revenue!AF35*Assumptions!C45 | AG5: =Revenue!AG35*Assumptions!C45 | AH5: =Revenue!AH35*Assumptions!C45 | AI5: =Revenue!AI35*Assumptions!C45 | AJ5: =Revenue!AJ35*Assumptions!C45 | AK5: =Revenue!AK35*Assumptions!C45 | AL5: =Revenue!AL35*Assumptions!C45 | AM5: =Revenue!AM35*Assumptions!C45 | AN5: =Revenue!AN35*Assumptions!C45 | AO5: =SUM(AC5:AN5)
B6: Wine / Beverage COGS (50%) | C6: =Revenue!C38*Assumptions!C46 | D6: =Revenue!D38*Assumptions!C46 | E6: =Revenue!E38*Assumptions!C46 | F6: =Revenue!F38*Assumptions!C46 | G6: =Revenue!G38*Assumptions!C46 | H6: =Revenue!H38*Assumptions!C46 | I6: =Revenue!I38*Assumptions!C46 | J6: =Revenue!J38*Assumptions!C46 | K6: =Revenue!K38*Assumptions!C46 | L6: =Revenue!L38*Assumptions!C46 | M6: =Revenue!M38*Assumptions!C46 | N6: =Revenue!N38*Assumptions!C46 | O6: =SUM(C6:N6) | P6: =Revenue!P38*Assumptions!C46 | Q6: =Revenue!Q38*Assumptions!C46 | R6: =Revenue!R38*Assumptions!C46 | S6: =Revenue!S38*Assumptions!C46 | T6: =Revenue!T38*Assumptions!C46 | U6: =Revenue!U38*Assumptions!C46 | V6: =Revenue!V38*Assumptions!C46 | W6: =Revenue!W38*Assumptions!C46 | X6: =Revenue!X38*Assumptions!C46 | Y6: =Revenue!Y38*Assumptions!C46 | Z6: =Revenue!Z38*Assumptions!C46 | AA6: =Revenue!AA38*Assumptions!C46 | AB6: =SUM(P6:AA6) | AC6: =Revenue!AC38*Assumptions!C46 | AD6: =Revenue!AD38*Assumptions!C46 | AE6: =Revenue!AE38*Assumptions!C46 | AF6: =Revenue!AF38*Assumptions!C46 | AG6: =Revenue!AG38*Assumptions!C46 | AH6: =Revenue!AH38*Assumptions!C46 | AI6: =Revenue!AI38*Assumptions!C46 | AJ6: =Revenue!AJ38*Assumptions!C46 | AK6: =Revenue!AK38*Assumptions!C46 | AL6: =Revenue!AL38*Assumptions!C46 | AM6: =Revenue!AM38*Assumptions!C46 | AN6: =Revenue!AN38*Assumptions!C46 | AO6: =SUM(AC6:AN6)
B8: TOTAL COGS | C8: =C5+C6 | D8: =D5+D6 | E8: =E5+E6 | F8: =F5+F6 | G8: =G5+G6 | H8: =H5+H6 | I8: =I5+I6 | J8: =J5+J6 | ... N8: =N5+N6 | O8: =SUM(C8:N8) | P8: =P5+P6 | Q8: =Q5+Q6 | R8: =R5+R6 | S8: =S5+S6 | T8: =T5+T6 | U8: =U5+U6 | V8: =V5+V6 | W8: =W5+W6 | ... AA8: =AA5+AA6 | AB8: =SUM(P8:AA8) | AC8: =AC5+AC6 | AD8: =AD5+AD6 | AE8: =AE5+AE6 | AF8: =AF5+AF6 | AG8: =AG5+AG6 | AH8: =AH5+AH6 | AI8: =AI5+AI6 | AJ8: =AJ5+AJ6 | ... AN8: =AN5+AN6 | AO8: =SUM(AC8:AN8)
B10: GROSS PROFIT | C10: =Revenue!C30-C8 | D10: =Revenue!D30-D8 | E10: =Revenue!E30-E8 | F10: =Revenue!F30-F8 | G10: =Revenue!G30-G8 | H10: =Revenue!H30-H8 | I10: =Revenue!I30-I8 | J10: =Revenue!J30-J8 | ... N10: =Revenue!N30-N8 | O10: =SUM(C10:N10) | P10: =Revenue!P30-P8 | Q10: =Revenue!Q30-Q8 | R10: =Revenue!R30-R8 | S10: =Revenue!S30-S8 | T10: =Revenue!T30-T8 | U10: =Revenue!U30-U8 | V10: =Revenue!V30-V8 | W10: =Revenue!W30-W8 | ... AA10: =Revenue!AA30-AA8 | AB10: =SUM(P10:AA10) | AC10: =Revenue!AC30-AC8 | AD10: =Revenue!AD30-AD8 | AE10: =Revenue!AE30-AE8 | AF10: =Revenue!AF30-AF8 | AG10: =Revenue!AG30-AG8 | AH10: =Revenue!AH30-AH8 | AI10: =Revenue!AI30-AI8 | AJ10: =Revenue!AJ30-AJ8 | ... AN10: =Revenue!AN30-AN8 | AO10: =SUM(AC10:AN10)
B11: Gross Margin % | C11: =IF(Revenue!C30=0,0,C10/Revenue!C30) | D11: =IF(Revenue!D30=0,0,D10/Revenue!D30) | E11: =IF(Revenue!E30=0,0,E10/Revenue!E30) | F11: =IF(Revenue!F30=0,0,F10/Revenue!F30) | G11: =IF(Revenue!G30=0,0,G10/Revenue!G30) | H11: =IF(Revenue!H30=0,0,H10/Revenue!H30) | I11: =IF(Revenue!I30=0,0,I10/Revenue!I30) | J11: =IF(Revenue!J30=0,0,J10/Revenue!J30) | ... AO11: =IF(Revenue!AO30=0,0,AO10/Revenue!AO30)

Sheet OpEx
B1: OPERATING EXPENSES
C3: M1 | D3: M2 | E3: M3 | F3: M4 | G3: M5 | H3: M6 | I3: M7 | J3: M8 | K3: M9 | L3: M10 | M3: M11 | N3: M12 | O3: Year 1 | P3: M13 | Q3: M14 | R3: M15 | S3: M16 | T3: M17 | U3: M18 | V3: M19 | W3: M20 | X3: M21 | Y3: M22 | Z3: M23 | AA3: M24 | AB3: Year 2 | AC3: M25 | AD3: M26 | AE3: M27 | AF3: M28 | AG3: M29 | AH3: M30 | AI3: M31 | AJ3: M32 | AK3: M33 | AL3: M34 | AM3: M35 | AN3: M36 | AO3: Year 3
B4: OpEx Inflation Multiplier | C4: 1 | D4: 1 | E4: 1 | F4: 1 | G4: 1 | H4: 1 | I4: 1 | J4: 1 | K4: 1 | L4: 1 | M4: 1 | N4: 1 | P4: =1+Assumptions!H52 | Q4: =1+Assumptions!H52 | R4: =1+Assumptions!H52 | S4: =1+Assumptions!H52 | T4: =1+Assumptions!H52 | U4: =1+Assumptions!H52 | V4: =1+Assumptions!H52 | W4: =1+Assumptions!H52 | X4: =1+Assumptions!H52 | Y4: =1+Assumptions!H52 | Z4: =1+Assumptions!H52 | AA4: =1+Assumptions!H52 | AC4: =(1+Assumptions!H52)^2 | AD4: =(1+Assumptions!H52)^2 | AE4: =(1+Assumptions!H52)^2 | AF4: =(1+Assumptions!H52)^2 | AG4: =(1+Assumptions!H52)^2 | AH4: =(1+Assumptions!H52)^2 | AI4: =(1+Assumptions!H52)^2 | AJ4: =(1+Assumptions!H52)^2 | AK4: =(1+Assumptions!H52)^2 | AL4: =(1+Assumptions!H52)^2 | AM4: =(1+Assumptions!H52)^2 | AN4: =(1+Assumptions!H52)^2
B5: Salary Inflation Multiplier | C5: 1 | D5: 1 | E5: 1 | F5: 1 | G5: 1 | H5: 1 | I5: 1 | J5: 1 | K5: 1 | L5: 1 | M5: 1 | N5: 1 | P5: =1+Assumptions!H51 | Q5: =1+Assumptions!H51 | R5: =1+Assumptions!H51 | S5: =1+Assumptions!H51 | T5: =1+Assumptions!H51 | U5: =1+Assumptions!H51 | V5: =1+Assumptions!H51 | W5: =1+Assumptions!H51 | X5: =1+Assumptions!H51 | Y5: =1+Assumptions!H51 | Z5: =1+Assumptions!H51 | AA5: =1+Assumptions!H51 | AC5: =(1+Assumptions!H51)^2 | AD5: =(1+Assumptions!H51)^2 | AE5: =(1+Assumptions!H51)^2 | AF5: =(1+Assumptions!H51)^2 | AG5: =(1+Assumptions!H51)^2 | AH5: =(1+Assumptions!H51)^2 | AI5: =(1+Assumptions!H51)^2 | AJ5: =(1+Assumptions!H51)^2 | AK5: =(1+Assumptions!H51)^2 | AL5: =(1+Assumptions!H51)^2 | AM5: =(1+Assumptions!H51)^2 | AN5: =(1+Assumptions!H51)^2
B7: STAFF COSTS
B8: Wages & Salaries | C8: =Assumptions!H21*C5 | D8: =Assumptions!H21*D5 | E8: =Assumptions!H21*E5 | F8: =Assumptions!H21*F5 | G8: =Assumptions!H21*G5 | H8: =Assumptions!H21*H5 | I8: =Assumptions!H21*I5 | J8: =Assumptions!H21*J5 | K8: =Assumptions!H21*K5 | L8: =Assumptions!H21*L5 | M8: =Assumptions!H21*M5 | N8: =Assumptions!H21*N5 | O8: =SUM(C8:N8) | P8: =Assumptions!H21*P5 | Q8: =Assumptions!H21*Q5 | R8: =Assumptions!H21*R5 | S8: =Assumptions!H21*S5 | T8: =Assumptions!H21*T5 | U8: =Assumptions!H21*U5 | V8: =Assumptions!H21*V5 | W8: =Assumptions!H21*W5 | X8: =Assumptions!H21*X5 | Y8: =Assumptions!H21*Y5 | Z8: =Assumptions!H21*Z5 | AA8: =Assumptions!H21*AA5 | AB8: =SUM(P8:AA8) | AC8: =Assumptions!H21*AC5 | AD8: =Assumptions!H21*AD5 | AE8: =Assumptions!H21*AE5 | AF8: =Assumptions!H21*AF5 | AG8: =Assumptions!H21*AG5 | AH8: =Assumptions!H21*AH5 | AI8: =Assumptions!H21*AI5 | AJ8: =Assumptions!H21*AJ5 | AK8: =Assumptions!H21*AK5 | AL8: =Assumptions!H21*AL5 | AM8: =Assumptions!H21*AM5 | AN8: =Assumptions!H21*AN5 | AO8: =SUM(AC8:AN8)
B9: MPF — Employer Contribution | C9: =(Assumptions!H21*Assumptions!H22)*C5 | D9: =(Assumptions!H21*Assumptions!H22)*D5 | E9: =(Assumptions!H21*Assumptions!H22)*E5 | F9: =(Assumptions!H21*Assumptions!H22)*F5 | G9: =(Assumptions!H21*Assumptions!H22)*G5 | H9: =(Assumptions!H21*Assumptions!H22)*H5 | I9: =(Assumptions!H21*Assumptions!H22)*I5 | J9: =(Assumptions!H21*Assumptions!H22)*J5 | K9: =(Assumptions!H21*Assumptions!H22)*K5 | L9: =(Assumptions!H21*Assumptions!H22)*L5 | M9: =(Assumptions!H21*Assumptions!H22)*M5 | N9: =(Assumptions!H21*Assumptions!H22)*N5 | O9: =SUM(C9:N9) | P9: =(Assumptions!H21*Assumptions!H22)*P5 | Q9: =(Assumptions!H21*Assumptions!H22)*Q5 | R9: =(Assumptions!H21*Assumptions!H22)*R5 | S9: =(Assumptions!H21*Assumptions!H22)*S5 | T9: =(Assumptions!H21*Assumptions!H22)*T5 | U9: =(Assumptions!H21*Assumptions!H22)*U5 | V9: =(Assumptions!H21*Assumptions!H22)*V5 | W9: =(Assumptions!H21*Assumptions!H22)*W5 | X9: =(Assumptions!H21*Assumptions!H22)*X5 | Y9: =(Assumptions!H21*Assumptions!H22)*Y5 | Z9: =(Assumptions!H21*Assumptions!H22)*Z5 | AA9: =(Assumptions!H21*Assumptions!H22)*AA5 | AB9: =SUM(P9:AA9) | AC9: =(Assumptions!H21*Assumptions!H22)*AC5 | AD9: =(Assumptions!H21*Assumptions!H22)*AD5 | AE9: =(Assumptions!H21*Assumptions!H22)*AE5 | AF9: =(Assumptions!H21*Assumptions!H22)*AF5 | AG9: =(Assumptions!H21*Assumptions!H22)*AG5 | AH9: =(Assumptions!H21*Assumptions!H22)*AH5 | AI9: =(Assumptions!H21*Assumptions!H22)*AI5 | AJ9: =(Assumptions!H21*Assumptions!H22)*AJ5 | AK9: =(Assumptions!H21*Assumptions!H22)*AK5 | AL9: =(Assumptions!H21*Assumptions!H22)*AL5 | AM9: =(Assumptions!H21*Assumptions!H22)*AM5 | AN9: =(Assumptions!H21*Assumptions!H22)*AN5 | AO9: =SUM(AC9:AN9)
B10: Additional Part-time / Casual Staff | C10: 0 | D10: 0 | E10: 0 | F10: 0 | G10: 0 | H10: 0 | I10: 0 | J10: 0 | K10: 0 | L10: 0 | M10: 0 | N10: 0 | O10: =SUM(C10:N10) | P10: 0 | Q10: 0 | R10: 0 | S10: 0 | T10: 0 | U10: 0 | V10: 0 | W10: 0 | X10: 0 | Y10: 0 | Z10: 0 | AA10: 0 | AB10: =SUM(P10:AA10) | AC10: 0 | AD10: 0 | AE10: 0 | AF10: 0 | AG10: 0 | AH10: 0 | AI10: 0 | AJ10: 0 | AK10: 0 | AL10: 0 | AM10: 0 | AN10: 0 | AO10: =SUM(AC10:AN10)
B11: Staff Welfare & Benefits | C11: =Assumptions!H47*C4 | D11: =Assumptions!H47*D4 | E11: =Assumptions!H47*E4 | F11: =Assumptions!H47*F4 | G11: =Assumptions!H47*G4 | H11: =Assumptions!H47*H4 | I11: =Assumptions!H47*I4 | J11: =Assumptions!H47*J4 | K11: =Assumptions!H47*K4 | L11: =Assumptions!H47*L4 | M11: =Assumptions!H47*M4 | N11: =Assumptions!H47*N4 | O11: =SUM(C11:N11) | P11: =Assumptions!H47*P4 | Q11: =Assumptions!H47*Q4 | R11: =Assumptions!H47*R4 | S11: =Assumptions!H47*S4 | T11: =Assumptions!H47*T4 | U11: =Assumptions!H47*U4 | V11: =Assumptions!H47*V4 | W11: =Assumptions!H47*W4 | X11: =Assumptions!H47*X4 | Y11: =Assumptions!H47*Y4 | Z11: =Assumptions!H47*Z4 | AA11: =Assumptions!H47*AA4 | AB11: =SUM(P11:AA11) | AC11: =Assumptions!H47*AC4 | AD11: =Assumptions!H47*AD4 | AE11: =Assumptions!H47*AE4 | AF11: =Assumptions!H47*AF4 | AG11: =Assumptions!H47*AG4 | AH11: =Assumptions!H47*AH4 | AI11: =Assumptions!H47*AI4 | AJ11: =Assumptions!H47*AJ4 | AK11: =Assumptions!H47*AK4 | AL11: =Assumptions!H47*AL4 | AM11: =Assumptions!H47*AM4 | AN11: =Assumptions!H47*AN4 | AO11: =SUM(AC11:AN11)
B13: RENT & OCCUPANCY
B14: Rent — Fixed | C14: =Assumptions!H32 | D14: =Assumptions!H32 | E14: =Assumptions!H32 | F14: =Assumptions!H32 | G14: =Assumptions!H32 | H14: =Assumptions!H32 | I14: =Assumptions!H32 | J14: =Assumptions!H32 | K14: =Assumptions!H32 | L14: =Assumptions!H32 | M14: =Assumptions!H32 | N14: =Assumptions!H32 | O14: =SUM(C14:N14) | P14: =Assumptions!H32 | Q14: =Assumptions!H32 | R14: =Assumptions!H32 | S14: =Assumptions!H32 | T14: =Assumptions!H32 | U14: =Assumptions!H32 | V14: =Assumptions!H32 | W14: =Assumptions!H32 | X14: =Assumptions!H32 | Y14: =Assumptions!H32 | Z14: =Assumptions!H32 | AA14: =Assumptions!H32 | AB14: =SUM(P14:AA14) | AC14: =Assumptions!H32 | AD14: =Assumptions!H32 | AE14: =Assumptions!H32 | AF14: =Assumptions!H32 | AG14: =Assumptions!H32 | AH14: =Assumptions!H32 | AI14: =Assumptions!H32 | AJ14: =Assumptions!H32 | AK14: =Assumptions!H32 | AL14: =Assumptions!H32 | AM14: =Assumptions!H32 | AN14: =Assumptions!H32 | AO14: =SUM(AC14:AN14)
B15: Rent — Variable (Turnover) | C15: =Revenue!C30*Assumptions!H33 | D15: =Revenue!D30*Assumptions!H33 | E15: =Revenue!E30*Assumptions!H33 | F15: =Revenue!F30*Assumptions!H33 | G15: =Revenue!G30*Assumptions!H33 | H15: =Revenue!H30*Assumptions!H33 | I15: =Revenue!I30*Assumptions!H33 | J15: =Revenue!J30*Assumptions!H33 | K15: =Revenue!K30*Assumptions!H33 | L15: =Revenue!L30*Assumptions!H33 | M15: =Revenue!M30*Assumptions!H33 | N15: =Revenue!N30*Assumptions!H33 | O15: =SUM(C15:N15) | P15: =Revenue!P30*Assumptions!H33 | Q15: =Revenue!Q30*Assumptions!H33 | R15: =Revenue!R30*Assumptions!H33 | S15: =Revenue!S30*Assumptions!H33 | T15: =Revenue!T30*Assumptions!H33 | U15: =Revenue!U30*Assumptions!H33 | V15: =Revenue!V30*Assumptions!H33 | W15: =Revenue!W30*Assumptions!H33 | X15: =Revenue!X30*Assumptions!H33 | Y15: =Revenue!Y30*Assumptions!H33 | Z15: =Revenue!Z30*Assumptions!H33 | AA15: =Revenue!AA30*Assumptions!H33 | AB15: =SUM(P15:AA15) | AC15: =Revenue!AC30*Assumptions!H33 | AD15: =Revenue!AD30*Assumptions!H33 | AE15: =Revenue!AE30*Assumptions!H33 | AF15: =Revenue!AF30*Assumptions!H33 | AG15: =Revenue!AG30*Assumptions!H33 | AH15: =Revenue!AH30*Assumptions!H33 | AI15: =Revenue!AI30*Assumptions!H33 | AJ15: =Revenue!AJ30*Assumptions!H33 | AK15: =Revenue!AK30*Assumptions!H33 | AL15: =Revenue!AL30*Assumptions!H33 | AM15: =Revenue!AM30*Assumptions!H33 | AN15: =Revenue!AN30*Assumptions!H33 | AO15: =SUM(AC15:AN15)
B16: Building Management Fee | C16: =Assumptions!H34*C4 | D16: =Assumptions!H34*D4 | E16: =Assumptions!H34*E4 | F16: =Assumptions!H34*F4 | G16: =Assumptions!H34*G4 | H16: =Assumptions!H34*H4 | I16: =Assumptions!H34*I4 | J16: =Assumptions!H34*J4 | K16: =Assumptions!H34*K4 | L16: =Assumptions!H34*L4 | M16: =Assumptions!H34*M4 | N16: =Assumptions!H34*N4 | O16: =SUM(C16:N16) | P16: =Assumptions!H34*P4 | Q16: =Assumptions!H34*Q4 | R16: =Assumptions!H34*R4 | S16: =Assumptions!H34*S4 | T16: =Assumptions!H34*T4 | U16: =Assumptions!H34*U4 | V16: =Assumptions!H34*V4 | W16: =Assumptions!H34*W4 | X16: =Assumptions!H34*X4 | Y16: =Assumptions!H34*Y4 | Z16: =Assumptions!H34*Z4 | AA16: =Assumptions!H34*AA4 | AB16: =SUM(P16:AA16) | AC16: =Assumptions!H34*AC4 | AD16: =Assumptions!H34*AD4 | AE16: =Assumptions!H34*AE4 | AF16: =Assumptions!H34*AF4 | AG16: =Assumptions!H34*AG4 | AH16: =Assumptions!H34*AH4 | AI16: =Assumptions!H34*AI4 | AJ16: =Assumptions!H34*AJ4 | AK16: =Assumptions!H34*AK4 | AL16: =Assumptions!H34*AL4 | AM16: =Assumptions!H34*AM4 | AN16: =Assumptions!H34*AN4 | AO16: =SUM(AC16:AN16)
B17: Rates | C17: =Assumptions!H37*C4 | D17: =Assumptions!H37*D4 | E17: =Assumptions!H37*E4 | F17: =Assumptions!H37*F4 | G17: =Assumptions!H37*G4 | H17: =Assumptions!H37*H4 | I17: =Assumptions!H37*I4 | J17: =Assumptions!H37*J4 | K17: =Assumptions!H37*K4 | L17: =Assumptions!H37*L4 | M17: =Assumptions!H37*M4 | N17: =Assumptions!H37*N4 | O17: =SUM(C17:N17) | P17: =Assumptions!H37*P4 | Q17: =Assumptions!H37*Q4 | R17: =Assumptions!H37*R4 | S17: =Assumptions!H37*S4 | T17: =Assumptions!H37*T4 | U17: =Assumptions!H37*U4 | V17: =Assumptions!H37*V4 | W17: =Assumptions!H37*W4 | X17: =Assumptions!H37*X4 | Y17: =Assumptions!H37*Y4 | Z17: =Assumptions!H37*Z4 | AA17: =Assumptions!H37*AA4 | AB17: =SUM(P17:AA17) | AC17: =Assumptions!H37*AC4 | AD17: =Assumptions!H37*AD4 | AE17: =Assumptions!H37*AE4 | AF17: =Assumptions!H37*AF4 | AG17: =Assumptions!H37*AG4 | AH17: =Assumptions!H37*AH4 | AI17: =Assumptions!H37*AI4 | AJ17: =Assumptions!H37*AJ4 | AK17: =Assumptions!H37*AK4 | AL17: =Assumptions!H37*AL4 | AM17: =Assumptions!H37*AM4 | AN17: =Assumptions!H37*AN4 | AO17: =SUM(AC17:AN17)
B19: UTILITIES & FACILITIES
B20: Electricity / Water / Gas | C20: =Assumptions!H35*C4 | D20: =Assumptions!H35*D4 | E20: =Assumptions!H35*E4 | F20: =Assumptions!H35*F4 | G20: =Assumptions!H35*G4 | H20: =Assumptions!H35*H4 | I20: =Assumptions!H35*I4 | J20: =Assumptions!H35*J4 | K20: =Assumptions!H35*K4 | L20: =Assumptions!H35*L4 | M20: =Assumptions!H35*M4 | N20: =Assumptions!H35*N4 | O20: =SUM(C20:N20) | P20: =Assumptions!H35*P4 | Q20: =Assumptions!H35*Q4 | R20: =Assumptions!H35*R4 | S20: =Assumptions!H35*S4 | T20: =Assumptions!H35*T4 | U20: =Assumptions!H35*U4 | V20: =Assumptions!H35*V4 | W20: =Assumptions!H35*W4 | X20: =Assumptions!H35*X4 | Y20: =Assumptions!H35*Y4 | Z20: =Assumptions!H35*Z4 | AA20: =Assumptions!H35*AA4 | AB20: =SUM(P20:AA20) | AC20: =Assumptions!H35*AC4 | AD20: =Assumptions!H35*AD4 | AE20: =Assumptions!H35*AE4 | AF20: =Assumptions!H35*AF4 | AG20: =Assumptions!H35*AG4 | AH20: =Assumptions!H35*AH4 | AI20: =Assumptions!H35*AI4 | AJ20: =Assumptions!H35*AJ4 | AK20: =Assumptions!H35*AK4 | AL20: =Assumptions!H35*AL4 | AM20: =Assumptions!H35*AM4 | AN20: =Assumptions!H35*AN4 | AO20: =SUM(AC20:AN20)
B21: Insurance | C21: =Assumptions!H36*C4 | D21: =Assumptions!H36*D4 | E21: =Assumptions!H36*E4 | F21: =Assumptions!H36*F4 | G21: =Assumptions!H36*G4 | H21: =Assumptions!H36*H4 | I21: =Assumptions!H36*I4 | J21: =Assumptions!H36*J4 | K21: =Assumptions!H36*K4 | L21: =Assumptions!H36*L4 | M21: =Assumptions!H36*M4 | N21: =Assumptions!H36*N4 | O21: =SUM(C21:N21) | P21: =Assumptions!H36*P4 | Q21: =Assumptions!H36*Q4 | R21: =Assumptions!H36*R4 | S21: =Assumptions!H36*S4 | T21: =Assumptions!H36*T4 | U21: =Assumptions!H36*U4 | V21: =Assumptions!H36*V4 | W21: =Assumptions!H36*W4 | X21: =Assumptions!H36*X4 | Y21: =Assumptions!H36*Y4 | Z21: =Assumptions!H36*Z4 | AA21: =Assumptions!H36*AA4 | AB21: =SUM(P21:AA21) | AC21: =Assumptions!H36*AC4 | AD21: =Assumptions!H36*AD4 | AE21: =Assumptions!H36*AE4 | AF21: =Assumptions!H36*AF4 | AG21: =Assumptions!H36*AG4 | AH21: =Assumptions!H36*AH4 | AI21: =Assumptions!H36*AI4 | AJ21: =Assumptions!H36*AJ4 | AK21: =Assumptions!H36*AK4 | AL21: =Assumptions!H36*AL4 | AM21: =Assumptions!H36*AM4 | AN21: =Assumptions!H36*AN4 | AO21: =SUM(AC21:AN21)
B22: Cleaning | C22: =Assumptions!H38*C4 | D22: =Assumptions!H38*D4 | E22: =Assumptions!H38*E4 | F22: =Assumptions!H38*F4 | G22: =Assumptions!H38*G4 | H22: =Assumptions!H38*H4 | I22: =Assumptions!H38*I4 | J22: =Assumptions!H38*J4 | K22: =Assumptions!H38*K4 | L22: =Assumptions!H38*L4 | M22: =Assumptions!H38*M4 | N22: =Assumptions!H38*N4 | O22: =SUM(C22:N22) | P22: =Assumptions!H38*P4 | Q22: =Assumptions!H38*Q4 | R22: =Assumptions!H38*R4 | S22: =Assumptions!H38*S4 | T22: =Assumptions!H38*T4 | U22: =Assumptions!H38*U4 | V22: =Assumptions!H38*V4 | W22: =Assumptions!H38*W4 | X22: =Assumptions!H38*X4 | Y22: =Assumptions!H38*Y4 | Z22: =Assumptions!H38*Z4 | AA22: =Assumptions!H38*AA4 | AB22: =SUM(P22:AA22) | AC22: =Assumptions!H38*AC4 | AD22: =Assumptions!H38*AD4 | AE22: =Assumptions!H38*AE4 | AF22: =Assumptions!H38*AF4 | AG22: =Assumptions!H38*AG4 | AH22: =Assumptions!H38*AH4 | AI22: =Assumptions!H38*AI4 | AJ22: =Assumptions!H38*AJ4 | AK22: =Assumptions!H38*AK4 | AL22: =Assumptions!H38*AL4 | AM22: =Assumptions!H38*AM4 | AN22: =Assumptions!H38*AN4 | AO22: =SUM(AC22:AN22)
B23: Garbage / Disposal | C23: =Assumptions!H45*C4 | D23: =Assumptions!H45*D4 | E23: =Assumptions!H45*E4 | F23: =Assumptions!H45*F4 | G23: =Assumptions!H45*G4 | H23: =Assumptions!H45*H4 | I23: =Assumptions!H45*I4 | J23: =Assumptions!H45*J4 | K23: =Assumptions!H45*K4 | L23: =Assumptions!H45*L4 | M23: =Assumptions!H45*M4 | N23: =Assumptions!H45*N4 | O23: =SUM(C23:N23) | P23: =Assumptions!H45*P4 | Q23: =Assumptions!H45*Q4 | R23: =Assumptions!H45*R4 | S23: =Assumptions!H45*S4 | T23: =Assumptions!H45*T4 | U23: =Assumptions!H45*U4 | V23: =Assumptions!H45*V4 | W23: =Assumptions!H45*W4 | X23: =Assumptions!H45*X4 | Y23: =Assumptions!H45*Y4 | Z23: =Assumptions!H45*Z4 | AA23: =Assumptions!H45*AA4 | AB23: =SUM(P23:AA23) | AC23: =Assumptions!H45*AC4 | AD23: =Assumptions!H45*AD4 | AE23: =Assumptions!H45*AE4 | AF23: =Assumptions!H45*AF4 | AG23: =Assumptions!H45*AG4 | AH23: =Assumptions!H45*AH4 | AI23: =Assumptions!H45*AI4 | AJ23: =Assumptions!H45*AJ4 | AK23: =Assumptions!H45*AK4 | AL23: =Assumptions!H45*AL4 | AM23: =Assumptions!H45*AM4 | AN23: =Assumptions!H45*AN4 | AO23: =SUM(AC23:AN23)
B24: Repairs & Maintenance | C24: =Assumptions!H46*C4 | D24: =Assumptions!H46*D4 | E24: =Assumptions!H46*E4 | F24: =Assumptions!H46*F4 | G24: =Assumptions!H46*G4 | H24: =Assumptions!H46*H4 | I24: =Assumptions!H46*I4 | J24: =Assumptions!H46*J4 | K24: =Assumptions!H46*K4 | L24: =Assumptions!H46*L4 | M24: =Assumptions!H46*M4 | N24: =Assumptions!H46*N4 | O24: =SUM(C24:N24) | P24: =Assumptions!H46*P4 | Q24: =Assumptions!H46*Q4 | R24: =Assumptions!H46*R4 | S24: =Assumptions!H46*S4 | T24: =Assumptions!H46*T4 | U24: =Assumptions!H46*U4 | V24: =Assumptions!H46*V4 | W24: =Assumptions!H46*W4 | X24: =Assumptions!H46*X4 | Y24: =Assumptions!H46*Y4 | Z24: =Assumptions!H46*Z4 | AA24: =Assumptions!H46*AA4 | AB24: =SUM(P24:AA24) | AC24: =Assumptions!H46*AC4 | AD24: =Assumptions!H46*AD4 | AE24: =Assumptions!H46*AE4 | AF24: =Assumptions!H46*AF4 | AG24: =Assumptions!H46*AG4 | AH24: =Assumptions!H46*AH4 | AI24: =Assumptions!H46*AI4 | AJ24: =Assumptions!H46*AJ4 | AK24: =Assumptions!H46*AK4 | AL24: =Assumptions!H46*AL4 | AM24: =Assumptions!H46*AM4 | AN24: =Assumptions!H46*AN4 | AO24: =SUM(AC24:AN24)
B26: ADMIN & MARKETING
B27: Credit Card Processing | C27: =Revenue!C30*Assumptions!H39 | D27: =Revenue!D30*Assumptions!H39 | E27: =Revenue!E30*Assumptions!H39 | F27: =Revenue!F30*Assumptions!H39 | G27: =Revenue!G30*Assumptions!H39 | H27: =Revenue!H30*Assumptions!H39 | I27: =Revenue!I30*Assumptions!H39 | J27: =Revenue!J30*Assumptions!H39 | K27: =Revenue!K30*Assumptions!H39 | L27: =Revenue!L30*Assumptions!H39 | M27: =Revenue!M30*Assumptions!H39 | N27: =Revenue!N30*Assumptions!H39 | O27: =SUM(C27:N27) | P27: =Revenue!P30*Assumptions!H39 | Q27: =Revenue!Q30*Assumptions!H39 | R27: =Revenue!R30*Assumptions!H39 | S27: =Revenue!S30*Assumptions!H39 | T27: =Revenue!T30*Assumptions!H39 | U27: =Revenue!U30*Assumptions!H39 | V27: =Revenue!V30*Assumptions!H39 | W27: =Revenue!W30*Assumptions!H39 | X27: =Revenue!X30*Assumptions!H39 | Y27: =Revenue!Y30*Assumptions!H39 | Z27: =Revenue!Z30*Assumptions!H39 | AA27: =Revenue!AA30*Assumptions!H39 | AB27: =SUM(P27:AA27) | AC27: =Revenue!AC30*Assumptions!H39 | AD27: =Revenue!AD30*Assumptions!H39 | AE27: =Revenue!AE30*Assumptions!H39 | AF27: =Revenue!AF30*Assumptions!H39 | AG27: =Revenue!AG30*Assumptions!H39 | AH27: =Revenue!AH30*Assumptions!H39 | AI27: =Revenue!AI30*Assumptions!H39 | AJ27: =Revenue!AJ30*Assumptions!H39 | AK27: =Revenue!AK30*Assumptions!H39 | AL27: =Revenue!AL30*Assumptions!H39 | AM27: =Revenue!AM30*Assumptions!H39 | AN27: =Revenue!AN30*Assumptions!H39 | AO27: =SUM(AC27:AN27)
B28: Marketing / PR | C28: =Assumptions!H40*C4 | D28: =Assumptions!H40*D4 | E28: =Assumptions!H40*E4 | F28: =Assumptions!H40*F4 | G28: =Assumptions!H40*G4 | H28: =Assumptions!H40*H4 | I28: =Assumptions!H40*I4 | J28: =Assumptions!H40*J4 | K28: =Assumptions!H40*K4 | L28: =Assumptions!H40*L4 | M28: =Assumptions!H40*M4 | N28: =Assumptions!H40*N4 | O28: =SUM(C28:N28) | P28: =Assumptions!H40*P4 | Q28: =Assumptions!H40*Q4 | R28: =Assumptions!H40*R4 | S28: =Assumptions!H40*S4 | T28: =Assumptions!H40*T4 | U28: =Assumptions!H40*U4 | V28: =Assumptions!H40*V4 | W28: =Assumptions!H40*W4 | X28: =Assumptions!H40*X4 | Y28: =Assumptions!H40*Y4 | Z28: =Assumptions!H40*Z4 | AA28: =Assumptions!H40*AA4 | AB28: =SUM(P28:AA28) | AC28: =Assumptions!H40*AC4 | AD28: =Assumptions!H40*AD4 | AE28: =Assumptions!H40*AE4 | AF28: =Assumptions!H40*AF4 | AG28: =Assumptions!H40*AG4 | AH28: =Assumptions!H40*AH4 | AI28: =Assumptions!H40*AI4 | AJ28: =Assumptions!H40*AJ4 | AK28: =Assumptions!H40*AK4 | AL28: =Assumptions!H40*AL4 | AM28: =Assumptions!H40*AM4 | AN28: =Assumptions!H40*AN4 | AO28: =SUM(AC28:AN28)
B29: Consulting & Accounting | C29: =Assumptions!H41*C4 | D29: =Assumptions!H41*D4 | E29: =Assumptions!H41*E4 | F29: =Assumptions!H41*F4 | G29: =Assumptions!H41*G4 | H29: =Assumptions!H41*H4 | I29: =Assumptions!H41*I4 | J29: =Assumptions!H41*J4 | K29: =Assumptions!H41*K4 | L29: =Assumptions!H41*L4 | M29: =Assumptions!H41*M4 | N29: =Assumptions!H41*N4 | O29: =SUM(C29:N29) | P29: =Assumptions!H41*P4 | Q29: =Assumptions!H41*Q4 | R29: =Assumptions!H41*R4 | S29: =Assumptions!H41*S4 | T29: =Assumptions!H41*T4 | U29: =Assumptions!H41*U4 | V29: =Assumptions!H41*V4 | W29: =Assumptions!H41*W4 | X29: =Assumptions!H41*X4 | Y29: =Assumptions!H41*Y4 | Z29: =Assumptions!H41*Z4 | AA29: =Assumptions!H41*AA4 | AB29: =SUM(P29:AA29) | AC29: =Assumptions!H41*AC4 | AD29: =Assumptions!H41*AD4 | AE29: =Assumptions!H41*AE4 | AF29: =Assumptions!H41*AF4 | AG29: =Assumptions!H41*AG4 | AH29: =Assumptions!H41*AH4 | AI29: =Assumptions!H41*AI4 | AJ29: =Assumptions!H41*AJ4 | AK29: =Assumptions!H41*AK4 | AL29: =Assumptions!H41*AL4 | AM29: =Assumptions!H41*AM4 | AN29: =Assumptions!H41*AN4 | AO29: =SUM(AC29:AN29)
B30: Restaurant Supplies | C30: =Assumptions!H42*C4 | D30: =Assumptions!H42*D4 | E30: =Assumptions!H42*E4 | F30: =Assumptions!H42*F4 | G30: =Assumptions!H42*G4 | H30: =Assumptions!H42*H4 | I30: =Assumptions!H42*I4 | J30: =Assumptions!H42*J4 | K30: =Assumptions!H42*K4 | L30: =Assumptions!H42*L4 | M30: =Assumptions!H42*M4 | N30: =Assumptions!H42*N4 | O30: =SUM(C30:N30) | P30: =Assumptions!H42*P4 | Q30: =Assumptions!H42*Q4 | R30: =Assumptions!H42*R4 | S30: =Assumptions!H42*S4 | T30: =Assumptions!H42*T4 | U30: =Assumptions!H42*U4 | V30: =Assumptions!H42*V4 | W30: =Assumptions!H42*W4 | X30: =Assumptions!H42*X4 | Y30: =Assumptions!H42*Y4 | Z30: =Assumptions!H42*Z4 | AA30: =Assumptions!H42*AA4 | AB30: =SUM(P30:AA30) | AC30: =Assumptions!H42*AC4 | AD30: =Assumptions!H42*AD4 | AE30: =Assumptions!H42*AE4 | AF30: =Assumptions!H42*AF4 | AG30: =Assumptions!H42*AG4 | AH30: =Assumptions!H42*AH4 | AI30: =Assumptions!H42*AI4 | AJ30: =Assumptions!H42*AJ4 | AK30: =Assumptions!H42*AK4 | AL30: =Assumptions!H42*AL4 | AM30: =Assumptions!H42*AM4 | AN30: =Assumptions!H42*AN4 | AO30: =SUM(AC30:AN30)
B31: Subscriptions & Telecom | C31: =Assumptions!H43*C4 | D31: =Assumptions!H43*D4 | E31: =Assumptions!H43*E4 | F31: =Assumptions!H43*F4 | G31: =Assumptions!H43*G4 | H31: =Assumptions!H43*H4 | I31: =Assumptions!H43*I4 | J31: =Assumptions!H43*J4 | K31: =Assumptions!H43*K4 | L31: =Assumptions!H43*L4 | M31: =Assumptions!H43*M4 | N31: =Assumptions!H43*N4 | O31: =SUM(C31:N31) | P31: =Assumptions!H43*P4 | Q31: =Assumptions!H43*Q4 | R31: =Assumptions!H43*R4 | S31: =Assumptions!H43*S4 | T31: =Assumptions!H43*T4 | U31: =Assumptions!H43*U4 | V31: =Assumptions!H43*V4 | W31: =Assumptions!H43*W4 | X31: =Assumptions!H43*X4 | Y31: =Assumptions!H43*Y4 | Z31: =Assumptions!H43*Z4 | AA31: =Assumptions!H43*AA4 | AB31: =SUM(P31:AA31) | AC31: =Assumptions!H43*AC4 | AD31: =Assumptions!H43*AD4 | AE31: =Assumptions!H43*AE4 | AF31: =Assumptions!H43*AF4 | AG31: =Assumptions!H43*AG4 | AH31: =Assumptions!H43*AH4 | AI31: =Assumptions!H43*AI4 | AJ31: =Assumptions!H43*AJ4 | AK31: =Assumptions!H43*AK4 | AL31: =Assumptions!H43*AL4 | AM31: =Assumptions!H43*AM4 | AN31: =Assumptions!H43*AN4 | AO31: =SUM(AC31:AN31)
B32: Other / Miscellaneous | C32: =Assumptions!H44*C4 | D32: =Assumptions!H44*D4 | E32: =Assumptions!H44*E4 | F32: =Assumptions!H44*F4 | G32: =Assumptions!H44*G4 | H32: =Assumptions!H44*H4 | I32: =Assumptions!H44*I4 | J32: =Assumptions!H44*J4 | K32: =Assumptions!H44*K4 | L32: =Assumptions!H44*L4 | M32: =Assumptions!H44*M4 | N32: =Assumptions!H44*N4 | O32: =SUM(C32:N32) | P32: =Assumptions!H44*P4 | Q32: =Assumptions!H44*Q4 | R32: =Assumptions!H44*R4 | S32: =Assumptions!H44*S4 | T32: =Assumptions!H44*T4 | U32: =Assumptions!H44*U4 | V32: =Assumptions!H44*V4 | W32: =Assumptions!H44*W4 | X32: =Assumptions!H44*X4 | Y32: =Assumptions!H44*Y4 | Z32: =Assumptions!H44*Z4 | AA32: =Assumptions!H44*AA4 | AB32: =SUM(P32:AA32) | AC32: =Assumptions!H44*AC4 | AD32: =Assumptions!H44*AD4 | AE32: =Assumptions!H44*AE4 | AF32: =Assumptions!H44*AF4 | AG32: =Assumptions!H44*AG4 | AH32: =Assumptions!H44*AH4 | AI32: =Assumptions!H44*AI4 | AJ32: =Assumptions!H44*AJ4 | AK32: =Assumptions!H44*AK4 | AL32: =Assumptions!H44*AL4 | AM32: =Assumptions!H44*AM4 | AN32: =Assumptions!H44*AN4 | AO32: =SUM(AC32:AN32)
B34: TOTAL OPERATING EXPENSES | C34: =C8+C9+C10+C11+C14+C15+C16+C17+C20+C21+C22+C23+C24+C27+C28+C29+C30+C31+C32 | D34: =D8+D9+D10+D11+D14+D15+D16+D17+D20+D21+D22+D23+D24+D27+D28+D29+D30+D31+D32 | E34: =E8+E9+E10+E11+E14+E15+E16+E17+E20+E21+E22+E23+E24+E27+E28+E29+E30+E31+E32 | F34: =F8+F9+F10+F11+F14+F15+F16+F17+F20+F21+F22+F23+F24+F27+F28+F29+F30+F31+F32 | G34: =G8+G9+G10+G11+G14+G15+G16+G17+G20+G21+G22+G23+G24+G27+G28+G29+G30+G31+G32 | H34: =H8+H9+H10+H11+H14+H15+H16+H17+H20+H21+H22+H23+H24+H27+H28+H29+H30+H31+H32 | I34: =I8+I9+I10+I11+I14+I15+I16+I17+I20+I21+I22+I23+I24+I27+I28+I29+I30+I31+I32 | J34: =J8+J9+J10+J11+J14+J15+J16+J17+J20+J21+J22+J23+J24+J27+J28+J29+J30+J31+J32 | ... N34: =N8+N9+N10+N11+N14+N15+N16+N17+N20+N21+N22+N23+N24+N27+N28+N29+N30+N31+N32 | O34: =SUM(C34:N34) | P34: =P8+P9+P10+P11+P14+P15+P16+P17+P20+P21+P22+P23+P24+P27+P28+P29+P30+P31+P32 | Q34: =Q8+Q9+Q10+Q11+Q14+Q15+Q16+Q17+Q20+Q21+Q22+Q23+Q24+Q27+Q28+Q29+Q30+Q31+Q32 | R34: =R8+R9+R10+R11+R14+R15+R16+R17+R20+R21+R22+R23+R24+R27+R28+R29+R30+R31+R32 | S34: =S8+S9+S10+S11+S14+S15+S16+S17+S20+S21+S22+S23+S24+S27+S28+S29+S30+S31+S32 | T34: =T8+T9+T10+T11+T14+T15+T16+T17+T20+T21+T22+T23+T24+T27+T28+T29+T30+T31+T32 | U34: =U8+U9+U10+U11+U14+U15+U16+U17+U20+U21+U22+U23+U24+U27+U28+U29+U30+U31+U32 | V34: =V8+V9+V10+V11+V14+V15+V16+V17+V20+V21+V22+V23+V24+V27+V28+V29+V30+V31+V32 | W34: =W8+W9+W10+W11+W14+W15+W16+W17+W20+W21+W22+W23+W24+W27+W28+W29+W30+W31+W32 | ... AA34: =AA8+AA9+AA10+AA11+AA14+AA15+AA16+AA17+AA20+AA21+AA22+AA23+AA24+AA27+AA28+AA29+AA30+AA31+AA32 | AB34: =SUM(P34:AA34) | AC34: =AC8+AC9+AC10+AC11+AC14+AC15+AC16+AC17+AC20+AC21+AC22+AC23+AC24+AC27+AC28+AC29+AC30+AC31+AC32 | AD34: =AD8+AD9+AD10+AD11+AD14+AD15+AD16+AD17+AD20+AD21+AD22+AD23+AD24+AD27+AD28+AD29+AD30+AD31+AD32 | AE34: =AE8+AE9+AE10+AE11+AE14+AE15+AE16+AE17+AE20+AE21+AE22+AE23+AE24+AE27+AE28+AE29+AE30+AE31+AE32 | AF34: =AF8+AF9+AF10+AF11+AF14+AF15+AF16+AF17+AF20+AF21+AF22+AF23+AF24+AF27+AF28+AF29+AF30+AF31+AF32 | AG34: =AG8+AG9+AG10+AG11+AG14+AG15+AG16+AG17+AG20+AG21+AG22+AG23+AG24+AG27+AG28+AG29+AG30+AG31+AG32 | AH34: =AH8+AH9+AH10+AH11+AH14+AH15+AH16+AH17+AH20+AH21+AH22+AH23+AH24+AH27+AH28+AH29+AH30+AH31+AH32 | AI34: =AI8+AI9+AI10+AI11+AI14+AI15+AI16+AI17+AI20+AI21+AI22+AI23+AI24+AI27+AI28+AI29+AI30+AI31+AI32 | AJ34: =AJ8+AJ9+AJ10+AJ11+AJ14+AJ15+AJ16+AJ17+AJ20+AJ21+AJ22+AJ23+AJ24+AJ27+AJ28+AJ29+AJ30+AJ31+AJ32 | ... AN34: =AN8+AN9+AN10+AN11+AN14+AN15+AN16+AN17+AN20+AN21+AN22+AN23+AN24+AN27+AN28+AN29+AN30+AN31+AN32 | AO34: =SUM(AC34:AN34)

Sheet P&L
B1: PROFIT & LOSS STATEMENT
B2: Project Chinois — Chinese Wine Bistro
C4: M1 | D4: M2 | E4: M3 | F4: M4 | G4: M5 | H4: M6 | I4: M7 | J4: M8 | K4: M9 | L4: M10 | M4: M11 | N4: M12 | O4: Year 1 | P4: M13 | Q4: M14 | R4: M15 | S4: M16 | T4: M17 | U4: M18 | V4: M19 | W4: M20 | X4: M21 | Y4: M22 | Z4: M23 | AA4: M24 | AB4: Year 2 | AC4: M25 | AD4: M26 | AE4: M27 | AF4: M28 | AG4: M29 | AH4: M30 | AI4: M31 | AJ4: M32 | AK4: M33 | AL4: M34 | AM4: M35 | AN4: M36 | AO4: Year 3
B6: Net Revenue | C6: =Revenue!C30 | D6: =Revenue!D30 | E6: =Revenue!E30 | F6: =Revenue!F30 | G6: =Revenue!G30 | H6: =Revenue!H30 | I6: =Revenue!I30 | J6: =Revenue!J30 | ... N6: =Revenue!N30 | O6: =SUM(C6:N6) | P6: =Revenue!P30 | Q6: =Revenue!Q30 | R6: =Revenue!R30 | S6: =Revenue!S30 | T6: =Revenue!T30 | U6: =Revenue!U30 | V6: =Revenue!V30 | W6: =Revenue!W30 | ... AA6: =Revenue!AA30 | AB6: =SUM(P6:AA6) | AC6: =Revenue!AC30 | AD6: =Revenue!AD30 | AE6: =Revenue!AE30 | AF6: =Revenue!AF30 | AG6: =Revenue!AG30 | AH6: =Revenue!AH30 | AI6: =Revenue!AI30 | AJ6: =Revenue!AJ30 | ... AN6: =Revenue!AN30 | AO6: =SUM(AC6:AN6)
B7: Food Revenue | C7: =Revenue!C35 | D7: =Revenue!D35 | E7: =Revenue!E35 | F7: =Revenue!F35 | G7: =Revenue!G35 | H7: =Revenue!H35 | I7: =Revenue!I35 | J7: =Revenue!J35 | ... N7: =Revenue!N35 | O7: =SUM(C7:N7) | P7: =Revenue!P35 | Q7: =Revenue!Q35 | R7: =Revenue!R35 | S7: =Revenue!S35 | T7: =Revenue!T35 | U7: =Revenue!U35 | V7: =Revenue!V35 | W7: =Revenue!W35 | ... AA7: =Revenue!AA35 | AB7: =SUM(P7:AA7) | AC7: =Revenue!AC35 | AD7: =Revenue!AD35 | AE7: =Revenue!AE35 | AF7: =Revenue!AF35 | AG7: =Revenue!AG35 | AH7: =Revenue!AH35 | AI7: =Revenue!AI35 | AJ7: =Revenue!AJ35 | ... AN7: =Revenue!AN35 | AO7: =SUM(AC7:AN7)
B8: Wine / Beverage Revenue | C8: =Revenue!C38 | D8: =Revenue!D38 | E8: =Revenue!E38 | F8: =Revenue!F38 | G8: =Revenue!G38 | H8: =Revenue!H38 | I8: =Revenue!I38 | J8: =Revenue!J38 | ... N8: =Revenue!N38 | O8: =SUM(C8:N8) | P8: =Revenue!P38 | Q8: =Revenue!Q38 | R8: =Revenue!R38 | S8: =Revenue!S38 | T8: =Revenue!T38 | U8: =Revenue!U38 | V8: =Revenue!V38 | W8: =Revenue!W38 | ... AA8: =Revenue!AA38 | AB8: =SUM(P8:AA8) | AC8: =Revenue!AC38 | AD8: =Revenue!AD38 | AE8: =Revenue!AE38 | AF8: =Revenue!AF38 | AG8: =Revenue!AG38 | AH8: =Revenue!AH38 | AI8: =Revenue!AI38 | AJ8: =Revenue!AJ38 | ... AN8: =Revenue!AN38 | AO8: =SUM(AC8:AN8)
B9: Service Charge | C9: =Revenue!C28 | D9: =Revenue!D28 | E9: =Revenue!E28 | F9: =Revenue!F28 | G9: =Revenue!G28 | H9: =Revenue!H28 | I9: =Revenue!I28 | J9: =Revenue!J28 | ... N9: =Revenue!N28 | O9: =SUM(C9:N9) | P9: =Revenue!P28 | Q9: =Revenue!Q28 | R9: =Revenue!R28 | S9: =Revenue!S28 | T9: =Revenue!T28 | U9: =Revenue!U28 | V9: =Revenue!V28 | W9: =Revenue!W28 | ... AA9: =Revenue!AA28 | AB9: =SUM(P9:AA9) | AC9: =Revenue!AC28 | AD9: =Revenue!AD28 | AE9: =Revenue!AE28 | AF9: =Revenue!AF28 | AG9: =Revenue!AG28 | AH9: =Revenue!AH28 | AI9: =Revenue!AI28 | AJ9: =Revenue!AJ28 | ... AN9: =Revenue!AN28 | AO9: =SUM(AC9:AN9)
B11: Cost of Goods Sold | C11: =COGS!C8 | D11: =COGS!D8 | E11: =COGS!E8 | F11: =COGS!F8 | G11: =COGS!G8 | H11: =COGS!H8 | I11: =COGS!I8 | J11: =COGS!J8 | ... N11: =COGS!N8 | O11: =SUM(C11:N11) | P11: =COGS!P8 | Q11: =COGS!Q8 | R11: =COGS!R8 | S11: =COGS!S8 | T11: =COGS!T8 | U11: =COGS!U8 | V11: =COGS!V8 | W11: =COGS!W8 | ... AA11: =COGS!AA8 | AB11: =SUM(P11:AA11) | AC11: =COGS!AC8 | AD11: =COGS!AD8 | AE11: =COGS!AE8 | AF11: =COGS!AF8 | AG11: =COGS!AG8 | AH11: =COGS!AH8 | AI11: =COGS!AI8 | AJ11: =COGS!AJ8 | ... AN11: =COGS!AN8 | AO11: =SUM(AC11:AN11)
B12: Food COGS | C12: =COGS!C5 | D12: =COGS!D5 | E12: =COGS!E5 | F12: =COGS!F5 | G12: =COGS!G5 | H12: =COGS!H5 | I12: =COGS!I5 | J12: =COGS!J5 | ... N12: =COGS!N5 | O12: =SUM(C12:N12) | P12: =COGS!P5 | Q12: =COGS!Q5 | R12: =COGS!R5 | S12: =COGS!S5 | T12: =COGS!T5 | U12: =COGS!U5 | V12: =COGS!V5 | W12: =COGS!W5 | ... AA12: =COGS!AA5 | AB12: =SUM(P12:AA12) | AC12: =COGS!AC5 | AD12: =COGS!AD5 | AE12: =COGS!AE5 | AF12: =COGS!AF5 | AG12: =COGS!AG5 | AH12: =COGS!AH5 | AI12: =COGS!AI5 | AJ12: =COGS!AJ5 | ... AN12: =COGS!AN5 | AO12: =SUM(AC12:AN12)
B13: Wine COGS | C13: =COGS!C6 | D13: =COGS!D6 | E13: =COGS!E6 | F13: =COGS!F6 | G13: =COGS!G6 | H13: =COGS!H6 | I13: =COGS!I6 | J13: =COGS!J6 | ... N13: =COGS!N6 | O13: =SUM(C13:N13) | P13: =COGS!P6 | Q13: =COGS!Q6 | R13: =COGS!R6 | S13: =COGS!S6 | T13: =COGS!T6 | U13: =COGS!U6 | V13: =COGS!V6 | W13: =COGS!W6 | ... AA13: =COGS!AA6 | AB13: =SUM(P13:AA13) | AC13: =COGS!AC6 | AD13: =COGS!AD6 | AE13: =COGS!AE6 | AF13: =COGS!AF6 | AG13: =COGS!AG6 | AH13: =COGS!AH6 | AI13: =COGS!AI6 | AJ13: =COGS!AJ6 | ... AN13: =COGS!AN6 | AO13: =SUM(AC13:AN13)
B15: GROSS PROFIT | C15: =COGS!C10 | D15: =COGS!D10 | E15: =COGS!E10 | F15: =COGS!F10 | G15: =COGS!G10 | H15: =COGS!H10 | I15: =COGS!I10 | J15: =COGS!J10 | ... N15: =COGS!N10 | O15: =SUM(C15:N15) | P15: =COGS!P10 | Q15: =COGS!Q10 | R15: =COGS!R10 | S15: =COGS!S10 | T15: =COGS!T10 | U15: =COGS!U10 | V15: =COGS!V10 | W15: =COGS!W10 | ... AA15: =COGS!AA10 | AB15: =SUM(P15:AA15) | AC15: =COGS!AC10 | AD15: =COGS!AD10 | AE15: =COGS!AE10 | AF15: =COGS!AF10 | AG15: =COGS!AG10 | AH15: =COGS!AH10 | AI15: =COGS!AI10 | AJ15: =COGS!AJ10 | ... AN15: =COGS!AN10 | AO15: =SUM(AC15:AN15)
B16: Gross Margin % | C16: =IF(Revenue!C30=0,0,COGS!C10/Revenue!C30) | D16: =IF(Revenue!D30=0,0,COGS!D10/Revenue!D30) | E16: =IF(Revenue!E30=0,0,COGS!E10/Revenue!E30) | F16: =IF(Revenue!F30=0,0,COGS!F10/Revenue!F30) | G16: =IF(Revenue!G30=0,0,COGS!G10/Revenue!G30) | H16: =IF(Revenue!H30=0,0,COGS!H10/Revenue!H30) | I16: =IF(Revenue!I30=0,0,COGS!I10/Revenue!I30) | J16: =IF(Revenue!J30=0,0,COGS!J10/Revenue!J30) | ... AO16: =IF(Revenue!AO30=0,0,COGS!AO10/Revenue!AO30)
B18: Operating Expenses | C18: =OpEx!C34 | D18: =OpEx!D34 | E18: =OpEx!E34 | F18: =OpEx!F34 | G18: =OpEx!G34 | H18: =OpEx!H34 | I18: =OpEx!I34 | J18: =OpEx!J34 | ... N18: =OpEx!N34 | O18: =SUM(C18:N18) | P18: =OpEx!P34 | Q18: =OpEx!Q34 | R18: =OpEx!R34 | S18: =OpEx!S34 | T18: =OpEx!T34 | U18: =OpEx!U34 | V18: =OpEx!V34 | W18: =OpEx!W34 | ... AA18: =OpEx!AA34 | AB18: =SUM(P18:AA18) | AC18: =OpEx!AC34 | AD18: =OpEx!AD34 | AE18: =OpEx!AE34 | AF18: =OpEx!AF34 | AG18: =OpEx!AG34 | AH18: =OpEx!AH34 | AI18: =OpEx!AI34 | AJ18: =OpEx!AJ34 | ... AN18: =OpEx!AN34 | AO18: =SUM(AC18:AN18)
B19: Wages & Salaries | C19: =OpEx!C8 | D19: =OpEx!D8 | E19: =OpEx!E8 | F19: =OpEx!F8 | G19: =OpEx!G8 | H19: =OpEx!H8 | I19: =OpEx!I8 | J19: =OpEx!J8 | ... N19: =OpEx!N8 | O19: =SUM(C19:N19) | P19: =OpEx!P8 | Q19: =OpEx!Q8 | R19: =OpEx!R8 | S19: =OpEx!S8 | T19: =OpEx!T8 | U19: =OpEx!U8 | V19: =OpEx!V8 | W19: =OpEx!W8 | ... AA19: =OpEx!AA8 | AB19: =SUM(P19:AA19) | AC19: =OpEx!AC8 | AD19: =OpEx!AD8 | AE19: =OpEx!AE8 | AF19: =OpEx!AF8 | AG19: =OpEx!AG8 | AH19: =OpEx!AH8 | AI19: =OpEx!AI8 | AJ19: =OpEx!AJ8 | ... AN19: =OpEx!AN8 | AO19: =SUM(AC19:AN19)
B20: MPF — Employer Contribution | C20: =OpEx!C9 | D20: =OpEx!D9 | E20: =OpEx!E9 | F20: =OpEx!F9 | G20: =OpEx!G9 | H20: =OpEx!H9 | I20: =OpEx!I9 | J20: =OpEx!J9 | ... N20: =OpEx!N9 | O20: =SUM(C20:N20) | P20: =OpEx!P9 | Q20: =OpEx!Q9 | R20: =OpEx!R9 | S20: =OpEx!S9 | T20: =OpEx!T9 | U20: =OpEx!U9 | V20: =OpEx!V9 | W20: =OpEx!W9 | ... AA20: =OpEx!AA9 | AB20: =SUM(P20:AA20) | AC20: =OpEx!AC9 | AD20: =OpEx!AD9 | AE20: =OpEx!AE9 | AF20: =OpEx!AF9 | AG20: =OpEx!AG9 | AH20: =OpEx!AH9 | AI20: =OpEx!AI9 | AJ20: =OpEx!AJ9 | ... AN20: =OpEx!AN9 | AO20: =SUM(AC20:AN20)
B21: Part-time / Casual Staff | C21: =OpEx!C10 | D21: =OpEx!D10 | E21: =OpEx!E10 | F21: =OpEx!F10 | G21: =OpEx!G10 | H21: =OpEx!H10 | I21: =OpEx!I10 | J21: =OpEx!J10 | ... N21: =OpEx!N10 | O21: =SUM(C21:N21) | P21: =OpEx!P10 | Q21: =OpEx!Q10 | R21: =OpEx!R10 | S21: =OpEx!S10 | T21: =OpEx!T10 | U21: =OpEx!U10 | V21: =OpEx!V10 | W21: =OpEx!W10 | ... AA21: =OpEx!AA10 | AB21: =SUM(P21:AA21) | AC21: =OpEx!AC10 | AD21: =OpEx!AD10 | AE21: =OpEx!AE10 | AF21: =OpEx!AF10 | AG21: =OpEx!AG10 | AH21: =OpEx!AH10 | AI21: =OpEx!AI10 | AJ21: =OpEx!AJ10 | ... AN21: =OpEx!AN10 | AO21: =SUM(AC21:AN21)
B22: Staff Welfare & Benefits | C22: =OpEx!C11 | D22: =OpEx!D11 | E22: =OpEx!E11 | F22: =OpEx!F11 | G22: =OpEx!G11 | H22: =OpEx!H11 | I22: =OpEx!I11 | J22: =OpEx!J11 | ... N22: =OpEx!N11 | O22: =SUM(C22:N22) | P22: =OpEx!P11 | Q22: =OpEx!Q11 | R22: =OpEx!R11 | S22: =OpEx!S11 | T22: =OpEx!T11 | U22: =OpEx!U11 | V22: =OpEx!V11 | W22: =OpEx!W11 | ... AA22: =OpEx!AA11 | AB22: =SUM(P22:AA22) | AC22: =OpEx!AC11 | AD22: =OpEx!AD11 | AE22: =OpEx!AE11 | AF22: =OpEx!AF11 | AG22: =OpEx!AG11 | AH22: =OpEx!AH11 | AI22: =OpEx!AI11 | AJ22: =OpEx!AJ11 | ... AN22: =OpEx!AN11 | AO22: =SUM(AC22:AN22)
B24: Total Staff Costs | C24: =OpEx!C8+OpEx!C9+OpEx!C10+OpEx!C11 | D24: =OpEx!D8+OpEx!D9+OpEx!D10+OpEx!D11 | E24: =OpEx!E8+OpEx!E9+OpEx!E10+OpEx!E11 | F24: =OpEx!F8+OpEx!F9+OpEx!F10+OpEx!F11 | G24: =OpEx!G8+OpEx!G9+OpEx!G10+OpEx!G11 | H24: =OpEx!H8+OpEx!H9+OpEx!H10+OpEx!H11 | I24: =OpEx!I8+OpEx!I9+OpEx!I10+OpEx!I11 | J24: =OpEx!J8+OpEx!J9+OpEx!J10+OpEx!J11 | ... N24: =OpEx!N8+OpEx!N9+OpEx!N10+OpEx!N11 | O24: =SUM(C24:N24) | P24: =OpEx!P8+OpEx!P9+OpEx!P10+OpEx!P11 | Q24: =OpEx!Q8+OpEx!Q9+OpEx!Q10+OpEx!Q11 | R24: =OpEx!R8+OpEx!R9+OpEx!R10+OpEx!R11 | S24: =OpEx!S8+OpEx!S9+OpEx!S10+OpEx!S11 | T24: =OpEx!T8+OpEx!T9+OpEx!T10+OpEx!T11 | U24: =OpEx!U8+OpEx!U9+OpEx!U10+OpEx!U11 | V24: =OpEx!V8+OpEx!V9+OpEx!V10+OpEx!V11 | W24: =OpEx!W8+OpEx!W9+OpEx!W10+OpEx!W11 | ... AA24: =OpEx!AA8+OpEx!AA9+OpEx!AA10+OpEx!AA11 | AB24: =SUM(P24:AA24) | AC24: =OpEx!AC8+OpEx!AC9+OpEx!AC10+OpEx!AC11 | AD24: =OpEx!AD8+OpEx!AD9+OpEx!AD10+OpEx!AD11 | AE24: =OpEx!AE8+OpEx!AE9+OpEx!AE10+OpEx!AE11 | AF24: =OpEx!AF8+OpEx!AF9+OpEx!AF10+OpEx!AF11 | AG24: =OpEx!AG8+OpEx!AG9+OpEx!AG10+OpEx!AG11 | AH24: =OpEx!AH8+OpEx!AH9+OpEx!AH10+OpEx!AH11 | AI24: =OpEx!AI8+OpEx!AI9+OpEx!AI10+OpEx!AI11 | AJ24: =OpEx!AJ8+OpEx!AJ9+OpEx!AJ10+OpEx!AJ11 | ... AN24: =OpEx!AN8+OpEx!AN9+OpEx!AN10+OpEx!AN11 | AO24: =SUM(AC24:AN24)
B25: Staff Cost % of Revenue | C25: =IF(Revenue!C30=0,0,C24/Revenue!C30) | D25: =IF(Revenue!D30=0,0,D24/Revenue!D30) | E25: =IF(Revenue!E30=0,0,E24/Revenue!E30) | F25: =IF(Revenue!F30=0,0,F24/Revenue!F30) | G25: =IF(Revenue!G30=0,0,G24/Revenue!G30) | H25: =IF(Revenue!H30=0,0,H24/Revenue!H30) | I25: =IF(Revenue!I30=0,0,I24/Revenue!I30) | J25: =IF(Revenue!J30=0,0,J24/Revenue!J30) | ... AO25: =IF(Revenue!AO30=0,0,AO24/Revenue!AO30)
B27: Total Rent & Occupancy | C27: =OpEx!C14+OpEx!C15+OpEx!C16+OpEx!C17 | D27: =OpEx!D14+OpEx!D15+OpEx!D16+OpEx!D17 | E27: =OpEx!E14+OpEx!E15+OpEx!E16+OpEx!E17 | F27: =OpEx!F14+OpEx!F15+OpEx!F16+OpEx!F17 | G27: =OpEx!G14+OpEx!G15+OpEx!G16+OpEx!G17 | H27: =OpEx!H14+OpEx!H15+OpEx!H16+OpEx!H17 | I27: =OpEx!I14+OpEx!I15+OpEx!I16+OpEx!I17 | J27: =OpEx!J14+OpEx!J15+OpEx!J16+OpEx!J17 | ... N27: =OpEx!N14+OpEx!N15+OpEx!N16+OpEx!N17 | O27: =SUM(C27:N27) | P27: =OpEx!P14+OpEx!P15+OpEx!P16+OpEx!P17 | Q27: =OpEx!Q14+OpEx!Q15+OpEx!Q16+OpEx!Q17 | R27: =OpEx!R14+OpEx!R15+OpEx!R16+OpEx!R17 | S27: =OpEx!S14+OpEx!S15+OpEx!S16+OpEx!S17 | T27: =OpEx!T14+OpEx!T15+OpEx!T16+OpEx!T17 | U27: =OpEx!U14+OpEx!U15+OpEx!U16+OpEx!U17 | V27: =OpEx!V14+OpEx!V15+OpEx!V16+OpEx!V17 | W27: =OpEx!W14+OpEx!W15+OpEx!W16+OpEx!W17 | ... AA27: =OpEx!AA14+OpEx!AA15+OpEx!AA16+OpEx!AA17 | AB27: =SUM(P27:AA27) | AC27: =OpEx!AC14+OpEx!AC15+OpEx!AC16+OpEx!AC17 | AD27: =OpEx!AD14+OpEx!AD15+OpEx!AD16+OpEx!AD17 | AE27: =OpEx!AE14+OpEx!AE15+OpEx!AE16+OpEx!AE17 | AF27: =OpEx!AF14+OpEx!AF15+OpEx!AF16+OpEx!AF17 | AG27: =OpEx!AG14+OpEx!AG15+OpEx!AG16+OpEx!AG17 | AH27: =OpEx!AH14+OpEx!AH15+OpEx!AH16+OpEx!AH17 | AI27: =OpEx!AI14+OpEx!AI15+OpEx!AI16+OpEx!AI17 | AJ27: =OpEx!AJ14+OpEx!AJ15+OpEx!AJ16+OpEx!AJ17 | ... AN27: =OpEx!AN14+OpEx!AN15+OpEx!AN16+OpEx!AN17 | AO27: =SUM(AC27:AN27)
B28: Rent % of Revenue | C28: =IF(Revenue!C30=0,0,C27/Revenue!C30) | D28: =IF(Revenue!D30=0,0,D27/Revenue!D30) | E28: =IF(Revenue!E30=0,0,E27/Revenue!E30) | F28: =IF(Revenue!F30=0,0,F27/Revenue!F30) | G28: =IF(Revenue!G30=0,0,G27/Revenue!G30) | H28: =IF(Revenue!H30=0,0,H27/Revenue!H30) | I28: =IF(Revenue!I30=0,0,I27/Revenue!I30) | J28: =IF(Revenue!J30=0,0,J27/Revenue!J30) | ... AO28: =IF(Revenue!AO30=0,0,AO27/Revenue!AO30)
B30: EBITDA | C30: =C15-C18 | D30: =D15-D18 | E30: =E15-E18 | F30: =F15-F18 | G30: =G15-G18 | H30: =H15-H18 | I30: =I15-I18 | J30: =J15-J18 | ... N30: =N15-N18 | O30: =SUM(C30:N30) | P30: =P15-P18 | Q30: =Q15-Q18 | R30: =R15-R18 | S30: =S15-S18 | T30: =T15-T18 | U30: =U15-U18 | V30: =V15-V18 | W30: =W15-W18 | ... AA30: =AA15-AA18 | AB30: =SUM(P30:AA30) | AC30: =AC15-AC18 | AD30: =AD15-AD18 | AE30: =AE15-AE18 | AF30: =AF15-AF18 | AG30: =AG15-AG18 | AH30: =AH15-AH18 | AI30: =AI15-AI18 | AJ30: =AJ15-AJ18 | ... AN30: =AN15-AN18 | AO30: =SUM(AC30:AN30)
B31: EBITDA Margin % | C31: =IF(Revenue!C30=0,0,C30/Revenue!C30) | D31: =IF(Revenue!D30=0,0,D30/Revenue!D30) | E31: =IF(Revenue!E30=0,0,E30/Revenue!E30) | F31: =IF(Revenue!F30=0,0,F30/Revenue!F30) | G31: =IF(Revenue!G30=0,0,G30/Revenue!G30) | H31: =IF(Revenue!H30=0,0,H30/Revenue!H30) | I31: =IF(Revenue!I30=0,0,I30/Revenue!I30) | J31: =IF(Revenue!J30=0,0,J30/Revenue!J30) | ... AO31: =IF(Revenue!AO30=0,0,AO30/Revenue!AO30)
B33: Management Incentive Fee (12%) | C33: 0 | D33: 0 | E33: 0 | F33: 0 | G33: 0 | H33: 0 | I33: 0 | J33: 0 | K33: 0 | L33: 0 | M33: 0 | N33: 0 | O33: 0 | P33: =IF(P30>0,P30*Assumptions!H53,0) | Q33: =IF(Q30>0,Q30*Assumptions!H53,0) | R33: =IF(R30>0,R30*Assumptions!H53,0) | S33: =IF(S30>0,S30*Assumptions!H53,0) | T33: =IF(T30>0,T30*Assumptions!H53,0) | U33: =IF(U30>0,U30*Assumptions!H53,0) | V33: =IF(V30>0,V30*Assumptions!H53,0) | W33: =IF(W30>0,W30*Assumptions!H53,0) | X33: =IF(X30>0,X30*Assumptions!H53,0) | Y33: =IF(Y30>0,Y30*Assumptions!H53,0) | Z33: =IF(Z30>0,Z30*Assumptions!H53,0) | AA33: =IF(AA30>0,AA30*Assumptions!H53,0) | AB33: =SUM(P33:AA33) | AC33: =IF(AC30>0,AC30*Assumptions!H53,0) | AD33: =IF(AD30>0,AD30*Assumptions!H53,0) | AE33: =IF(AE30>0,AE30*Assumptions!H53,0) | AF33: =IF(AF30>0,AF30*Assumptions!H53,0) | AG33: =IF(AG30>0,AG30*Assumptions!H53,0) | AH33: =IF(AH30>0,AH30*Assumptions!H53,0) | AI33: =IF(AI30>0,AI30*Assumptions!H53,0) | AJ33: =IF(AJ30>0,AJ30*Assumptions!H53,0) | AK33: =IF(AK30>0,AK30*Assumptions!H53,0) | AL33: =IF(AL30>0,AL30*Assumptions!H53,0) | AM33: =IF(AM30>0,AM30*Assumptions!H53,0) | AN33: =IF(AN30>0,AN30*Assumptions!H53,0) | AO33: =SUM(AC33:AN33)
B35: NET INCOME (to Shareholders) | C35: =C30-C33 | D35: =D30-D33 | E35: =E30-E33 | F35: =F30-F33 | G35: =G30-G33 | H35: =H30-H33 | I35: =I30-I33 | J35: =J30-J33 | ... N35: =N30-N33 | O35: =SUM(C35:N35) | P35: =P30-P33 | Q35: =Q30-Q33 | R35: =R30-R33 | S35: =S30-S33 | T35: =T30-T33 | U35: =U30-U33 | V35: =V30-V33 | W35: =W30-W33 | ... AA35: =AA30-AA33 | AB35: =SUM(P35:AA35) | AC35: =AC30-AC33 | AD35: =AD30-AD33 | AE35: =AE30-AE33 | AF35: =AF30-AF33 | AG35: =AG30-AG33 | AH35: =AH30-AH33 | AI35: =AI30-AI33 | AJ35: =AJ30-AJ33 | ... AN35: =AN30-AN33 | AO35: =SUM(AC35:AN35)
B36: Net Margin % | C36: =IF(Revenue!C30=0,0,C35/Revenue!C30) | D36: =IF(Revenue!D30=0,0,D35/Revenue!D30) | E36: =IF(Revenue!E30=0,0,E35/Revenue!E30) | F36: =IF(Revenue!F30=0,0,F35/Revenue!F30) | G36: =IF(Revenue!G30=0,0,G35/Revenue!G30) | H36: =IF(Revenue!H30=0,0,H35/Revenue!H30) | I36: =IF(Revenue!I30=0,0,I35/Revenue!I30) | J36: =IF(Revenue!J30=0,0,J35/Revenue!J30) | ... AO36: =IF(Revenue!AO30=0,0,AO35/Revenue!AO30)
B42: EBITDA | C42: =C15-C18 | D42: =D15-D18 | E42: =E15-E18 | F42: =F15-F18 | G42: =G15-G18 | H42: =H15-H18 | I42: =I15-I18 | J42: =J15-J18 | ... N42: =N15-N18 | O42: =SUM(C42:N42) | P42: =P15-P18 | Q42: =Q15-Q18 | R42: =R15-R18 | S42: =S15-S18 | T42: =T15-T18 | U42: =U15-U18 | V42: =V15-V18 | W42: =W15-W18 | ... AA42: =AA15-AA18 | AB42: =SUM(P42:AA42) | AC42: =AC15-AC18 | AD42: =AD15-AD18 | AE42: =AE15-AE18 | AF42: =AF15-AF18 | AG42: =AG15-AG18 | AH42: =AH15-AH18 | AI42: =AI15-AI18 | AJ42: =AJ15-AJ18 | ... AN42: =AN15-AN18 | AO42: =SUM(AC42:AN42)
B43: EBITDA Margin % | C43: =IF(Revenue!C30=0,0,C42/Revenue!C30) | D43: =IF(Revenue!D30=0,0,D42/Revenue!D30) | E43: =IF(Revenue!E30=0,0,E42/Revenue!E30) | F43: =IF(Revenue!F30=0,0,F42/Revenue!F30) | G43: =IF(Revenue!G30=0,0,G42/Revenue!G30) | H43: =IF(Revenue!H30=0,0,H42/Revenue!H30) | I43: =IF(Revenue!I30=0,0,I42/Revenue!I30) | J43: =IF(Revenue!J30=0,0,J42/Revenue!J30) | ... AO43: =IF(Revenue!AO30=0,0,AO42/Revenue!AO30)
B45: Management Incentive Fee (12%) | C45: =IF(C42>0,C42*Assumptions!H53,0) | D45: =IF(D42>0,D42*Assumptions!H53,0) | E45: =IF(E42>0,E42*Assumptions!H53,0) | F45: =IF(F42>0,F42*Assumptions!H53,0) | G45: =IF(G42>0,G42*Assumptions!H53,0) | H45: =IF(H42>0,H42*Assumptions!H53,0) | I45: =IF(I42>0,I42*Assumptions!H53,0) | J45: =IF(J42>0,J42*Assumptions!H53,0) | K45: =IF(K42>0,K42*Assumptions!H53,0) | L45: =IF(L42>0,L42*Assumptions!H53,0) | M45: =IF(M42>0,M42*Assumptions!H53,0) | N45: =IF(N42>0,N42*Assumptions!H53,0) | O45: =SUM(C45:N45) | P45: =IF(P42>0,P42*Assumptions!H53,0) | Q45: =IF(Q42>0,Q42*Assumptions!H53,0) | R45: =IF(R42>0,R42*Assumptions!H53,0) | S45: =IF(S42>0,S42*Assumptions!H53,0) | T45: =IF(T42>0,T42*Assumptions!H53,0) | U45: =IF(U42>0,U42*Assumptions!H53,0) | V45: =IF(V42>0,V42*Assumptions!H53,0) | W45: =IF(W42>0,W42*Assumptions!H53,0) | X45: =IF(X42>0,X42*Assumptions!H53,0) | Y45: =IF(Y42>0,Y42*Assumptions!H53,0) | Z45: =IF(Z42>0,Z42*Assumptions!H53,0) | AA45: =IF(AA42>0,AA42*Assumptions!H53,0) | AB45: =SUM(P45:AA45) | AC45: =IF(AC42>0,AC42*Assumptions!H53,0) | AD45: =IF(AD42>0,AD42*Assumptions!H53,0) | AE45: =IF(AE42>0,AE42*Assumptions!H53,0) | AF45: =IF(AF42>0,AF42*Assumptions!H53,0) | AG45: =IF(AG42>0,AG42*Assumptions!H53,0) | AH45: =IF(AH42>0,AH42*Assumptions!H53,0) | AI45: =IF(AI42>0,AI42*Assumptions!H53,0) | AJ45: =IF(AJ42>0,AJ42*Assumptions!H53,0) | AK45: =IF(AK42>0,AK42*Assumptions!H53,0) | AL45: =IF(AL42>0,AL42*Assumptions!H53,0) | AM45: =IF(AM42>0,AM42*Assumptions!H53,0) | AN45: =IF(AN42>0,AN42*Assumptions!H53,0) | AO45: =SUM(AC45:AN45)
B47: NET INCOME (to Shareholders) | C47: =C42-C45 | D47: =D42-D45 | E47: =E42-E45 | F47: =F42-F45 | G47: =G42-G45 | H47: =H42-H45 | I47: =I42-I45 | J47: =J42-J45 | ... N47: =N42-N45 | O47: =SUM(C47:N47) | P47: =P42-P45 | Q47: =Q42-Q45 | R47: =R42-R45 | S47: =S42-S45 | T47: =T42-T45 | U47: =U42-U45 | V47: =V42-V45 | W47: =W42-W45 | ... AA47: =AA42-AA45 | AB47: =SUM(P47:AA47) | AC47: =AC42-AC45 | AD47: =AD42-AD45 | AE47: =AE42-AE45 | AF47: =AF42-AF45 | AG47: =AG42-AG45 | AH47: =AH42-AH45 | AI47: =AI42-AI45 | AJ47: =AJ42-AJ45 | ... AN47: =AN42-AN45 | AO47: =SUM(AC47:AN47)
B48: Net Margin % | C48: =IF(Revenue!C30=0,0,C47/Revenue!C30) | D48: =IF(Revenue!D30=0,0,D47/Revenue!D30) | E48: =IF(Revenue!E30=0,0,E47/Revenue!E30) | F48: =IF(Revenue!F30=0,0,F47/Revenue!F30) | G48: =IF(Revenue!G30=0,0,G47/Revenue!G30) | H48: =IF(Revenue!H30=0,0,H47/Revenue!H30) | I48: =IF(Revenue!I30=0,0,I47/Revenue!I30) | J48: =IF(Revenue!J30=0,0,J47/Revenue!J30) | ... AO48: =IF(Revenue!AO30=0,0,AO47/Revenue!AO30)

Sheet Investment
B1: INVESTMENT SUMMARY & RETURNS
B3: INITIAL INVESTMENT BREAKDOWN (HKD)
B4: Item | C4: Amount (HKD) | D4: % of Total
B5: Fit out: wine fridge, equipment & furniture | C5: 2546000 | D5: =C5/C15
B6: Rental & utility deposit | C6: 509000 | D6: =C6/C15
B7: First month rent & utilities | C7: 178000 | D7: =C7/C15
B8: Restaurant license & permits | C8: 143000 | D8: =C8/C15
B9: Pre-opening costs | C9: 287000 | D9: =C9/C15
B10: PR & marketing launch | C10: 255000 | D10: =C10/C15
B11: Design fee | C11: 318000 | D11: =C11/C15
B12: Contingency / spare | C12: 254000 | D12: =C12/C15
B13: Wine inventory (initial stock) | C13: 223000 | D13: =C13/C15
B14: Month 1 staff salary | C14: 287000 | D14: =C14/C15
B15: TOTAL INVESTMENT | C15: =SUM(C5:C14)
B17: RETURN METRICS
C18: Year 1 | D18: Year 2 | E18: Year 3
B19: Net Revenue | C19: ='P&L'!O6 | D19: ='P&L'!AB6 | E19: ='P&L'!AO6
B20: Gross Profit | C20: ='P&L'!O15 | D20: ='P&L'!AB15 | E20: ='P&L'!AO15
B21: EBITDA | C21: ='P&L'!O30 | D21: ='P&L'!AB30 | E21: ='P&L'!AO30
B22: EBITDA Margin | C22: ='P&L'!O31 | D22: ='P&L'!AB31 | E22: ='P&L'!AO31
B23: Net Income to Shareholders | C23: ='P&L'!O35 | D23: ='P&L'!AB35 | E23: ='P&L'!AO35
B24: Net Margin | C24: ='P&L'!O36 | D24: ='P&L'!AB36 | E24: ='P&L'!AO36
B26: Cumulative Net Income (3Y) | C26: ='P&L'!O35+'P&L'!AB35+'P&L'!AO35 | D26: ='P&L'!AB35 | E26: ='P&L'!AO35
B27: Return on Investment (3Y) | C27: =C26/C15
B28: Estimated Payback (months) | C28: =IF(('P&L'!O35+'P&L'!AB35+'P&L'!AO35)/36>0,C15/(('P&L'!O35+'P&L'!AB35+'P&L'!AO35)/36),0)
B30: DIVIDEND CAPACITY
B31: Assuming 100% payout after payback:
B32: Year 2 Dividend (if payback in Y1) | C32: ='P&L'!AB35
B33: Year 3 Dividend | C33: ='P&L'!AO35
B34: Dividend Yield on Investment (Y3) | C34: ='P&L'!AO35/Investment!C15
